{
  "mistakes": [
    {
      "prediction_date": "2016-01-03",
      "predicted_90d": 1.0,
      "actual_90d": -15.2,
      "error": 16.2,
      "direction_correct": "False",
      "composite_score": 51.6,
      "sector": "Petrochemicals",
      "rate_regime": "stable",
      "root_cause": "Model underestimated downside"
    },
    {
      "prediction_date": "2016-06-29",
      "predicted_90d": 5.5,
      "actual_90d": -25.5,
      "error": 31.0,
      "direction_correct": "False",
      "composite_score": 60.7,
      "sector": "Petrochemicals",
      "rate_regime": "stable",
      "root_cause": "Model underestimated downside"
    },
    {
      "prediction_date": "2016-09-27",
      "predicted_90d": 5.5,
      "actual_90d": 45.3,
      "error": 39.8,
      "direction_correct": "True",
      "composite_score": 66.2,
      "sector": "Petrochemicals",
      "rate_regime": "stable",
      "root_cause": "Model underestimated upside"
    },
    {
      "prediction_date": "2016-12-27",
      "predicted_90d": 3.0,
      "actual_90d": -17.4,
      "error": 20.4,
      "direction_correct": "False",
      "composite_score": 56.6,
      "sector": "Petrochemicals",
      "rate_regime": "stable",
      "root_cause": "Model underestimated downside"
    },
    {
      "prediction_date": "2017-12-21",
      "predicted_90d": 1.0,
      "actual_90d": 42.2,
      "error": 41.2,
      "direction_correct": "True",
      "composite_score": 50.6,
      "sector": "Petrochemicals",
      "rate_regime": "stable",
      "root_cause": "Model underestimated upside"
    },
    {
      "prediction_date": "2018-03-21",
      "predicted_90d": 1.0,
      "actual_90d": 20.9,
      "error": 19.9,
      "direction_correct": "True",
      "composite_score": 50.1,
      "sector": "Petrochemicals",
      "rate_regime": "stable",
      "root_cause": "Model underestimated upside"
    },
    {
      "prediction_date": "2018-06-19",
      "predicted_90d": -3.5,
      "actual_90d": -16.0,
      "error": 12.5,
      "direction_correct": "True",
      "composite_score": 45.5,
      "sector": "Petrochemicals",
      "rate_regime": "stable",
      "root_cause": "Model underestimated downside"
    },
    {
      "prediction_date": "2019-12-11",
      "predicted_90d": 0.0,
      "actual_90d": -25.7,
      "error": 25.7,
      "direction_correct": "True",
      "composite_score": 49.1,
      "sector": "Petrochemicals",
      "rate_regime": "falling",
      "root_cause": "Model underestimated downside"
    },
    {
      "prediction_date": "2020-03-10",
      "predicted_90d": 7.5,
      "actual_90d": 24.5,
      "error": 17.0,
      "direction_correct": "True",
      "composite_score": 72.2,
      "sector": "Petrochemicals",
      "rate_regime": "stable",
      "root_cause": "Model underestimated upside"
    },
    {
      "prediction_date": "2020-06-08",
      "predicted_90d": -4.5,
      "actual_90d": 111.3,
      "error": 115.8,
      "direction_correct": "False",
      "composite_score": 40.1,
      "sector": "Petrochemicals",
      "rate_regime": "falling",
      "root_cause": "Model underestimated upside"
    },
    {
      "prediction_date": "2020-09-06",
      "predicted_90d": 3.0,
      "actual_90d": 24.5,
      "error": 21.5,
      "direction_correct": "True",
      "composite_score": 53.9,
      "sector": "Petrochemicals",
      "rate_regime": "stable",
      "root_cause": "Model underestimated upside"
    },
    {
      "prediction_date": "2020-12-06",
      "predicted_90d": 5.5,
      "actual_90d": 113.3,
      "error": 107.8,
      "direction_correct": "True",
      "composite_score": 61.1,
      "sector": "Petrochemicals",
      "rate_regime": "stable",
      "root_cause": "Model underestimated upside"
    },
    {
      "prediction_date": "2021-06-03",
      "predicted_90d": 3.0,
      "actual_90d": -12.7,
      "error": 15.7,
      "direction_correct": "False",
      "composite_score": 55.6,
      "sector": "Petrochemicals",
      "rate_regime": "stable",
      "root_cause": "Model underestimated downside"
    },
    {
      "prediction_date": "2021-09-01",
      "predicted_90d": 3.0,
      "actual_90d": -17.4,
      "error": 20.4,
      "direction_correct": "False",
      "composite_score": 54.5,
      "sector": "Petrochemicals",
      "rate_regime": "stable",
      "root_cause": "Model underestimated downside"
    },
    {
      "prediction_date": "2022-02-28",
      "predicted_90d": 5.5,
      "actual_90d": -33.4,
      "error": 38.9,
      "direction_correct": "False",
      "composite_score": 61.7,
      "sector": "Petrochemicals",
      "rate_regime": "stable",
      "root_cause": "Sector weights may need tuning for Petrochemicals"
    },
    {
      "prediction_date": "2022-08-28",
      "predicted_90d": -8.5,
      "actual_90d": -28.0,
      "error": 19.5,
      "direction_correct": "True",
      "composite_score": 42.5,
      "sector": "Petrochemicals",
      "rate_regime": "rising",
      "root_cause": "Model underestimated downside"
    },
    {
      "prediction_date": "2023-02-23",
      "predicted_90d": -2.0,
      "actual_90d": 14.8,
      "error": 16.8,
      "direction_correct": "False",
      "composite_score": 57.9,
      "sector": "Petrochemicals",
      "rate_regime": "rising",
      "root_cause": "Model underestimated upside"
    },
    {
      "prediction_date": "2024-02-18",
      "predicted_90d": 1.0,
      "actual_90d": -18.9,
      "error": 19.9,
      "direction_correct": "False",
      "composite_score": 50.5,
      "sector": "Petrochemicals",
      "rate_regime": "stable",
      "root_cause": "Model underestimated downside"
    },
    {
      "prediction_date": "2024-11-14",
      "predicted_90d": 0.0,
      "actual_90d": -13.7,
      "error": 13.7,
      "direction_correct": "True",
      "composite_score": 48.3,
      "sector": "Petrochemicals",
      "rate_regime": "falling",
      "root_cause": "Model underestimated downside"
    },
    {
      "prediction_date": "2025-11-09",
      "predicted_90d": 3.0,
      "actual_90d": -16.3,
      "error": 19.3,
      "direction_correct": "False",
      "composite_score": 60.0,
      "sector": "Petrochemicals",
      "rate_regime": "stable",
      "root_cause": "Model underestimated downside"
    }
  ]
}