{
  "mistakes": [
    {
      "prediction_date": "2016-09-27",
      "predicted_90d": 7.0,
      "actual_90d": 29.8,
      "error": 22.8,
      "direction_correct": "True",
      "composite_score": 67.4,
      "fund_score": 40,
      "rate_regime": "stable",
      "rsi": 3.3,
      "vix": 13.1,
      "root_cause": "Model underestimated upside"
    },
    {
      "prediction_date": "2016-12-27",
      "predicted_90d": 5.0,
      "actual_90d": -10.4,
      "error": 15.4,
      "direction_correct": "False",
      "composite_score": 60.0,
      "fund_score": 40,
      "rate_regime": "stable",
      "rsi": 44.4,
      "vix": 12.0,
      "root_cause": "Model underestimated downside"
    },
    {
      "prediction_date": "2017-06-25",
      "predicted_90d": 3.0,
      "actual_90d": -16.9,
      "error": 19.9,
      "direction_correct": "False",
      "composite_score": 54.8,
      "fund_score": 73,
      "rate_regime": "stable",
      "rsi": 70.8,
      "vix": 10.5,
      "root_cause": "Model underestimated downside"
    },
    {
      "prediction_date": "2017-09-24",
      "predicted_90d": 9.0,
      "actual_90d": -10.0,
      "error": 19.0,
      "direction_correct": "False",
      "composite_score": 74.4,
      "fund_score": 73,
      "rate_regime": "stable",
      "rsi": 28.6,
      "vix": 9.7,
      "root_cause": "Model underestimated downside"
    },
    {
      "prediction_date": "2017-12-21",
      "predicted_90d": 5.0,
      "actual_90d": -21.4,
      "error": 26.4,
      "direction_correct": "False",
      "composite_score": 62.9,
      "fund_score": 73,
      "rate_regime": "stable",
      "rsi": 54.5,
      "vix": 9.6,
      "root_cause": "Model underestimated downside"
    },
    {
      "prediction_date": "2018-03-21",
      "predicted_90d": 5.0,
      "actual_90d": -16.9,
      "error": 21.9,
      "direction_correct": "False",
      "composite_score": 58.6,
      "fund_score": 44,
      "rate_regime": "stable",
      "rsi": 36.2,
      "vix": 17.9,
      "root_cause": "Model underestimated downside"
    },
    {
      "prediction_date": "2018-06-19",
      "predicted_90d": 3.0,
      "actual_90d": -12.5,
      "error": 15.5,
      "direction_correct": "False",
      "composite_score": 54.2,
      "fund_score": 44,
      "rate_regime": "stable",
      "rsi": 67.5,
      "vix": 13.4,
      "root_cause": "Model underestimated downside"
    },
    {
      "prediction_date": "2018-09-17",
      "predicted_90d": 3.0,
      "actual_90d": -14.9,
      "error": 17.9,
      "direction_correct": "False",
      "composite_score": 54.2,
      "fund_score": 44,
      "rate_regime": "stable",
      "rsi": 59.8,
      "vix": 13.7,
      "root_cause": "Model underestimated downside"
    },
    {
      "prediction_date": "2018-12-16",
      "predicted_90d": 3.0,
      "actual_90d": -10.6,
      "error": 13.6,
      "direction_correct": "False",
      "composite_score": 50.1,
      "fund_score": 44,
      "rate_regime": "stable",
      "rsi": 73.0,
      "vix": 20.6,
      "root_cause": "Model underestimated downside"
    },
    {
      "prediction_date": "2019-03-17",
      "predicted_90d": 3.0,
      "actual_90d": -12.0,
      "error": 15.0,
      "direction_correct": "False",
      "composite_score": 57.0,
      "fund_score": 30,
      "rate_regime": "stable",
      "rsi": 41.2,
      "vix": 13.5,
      "root_cause": "Model underestimated downside"
    },
    {
      "prediction_date": "2020-06-08",
      "predicted_90d": 0.0,
      "actual_90d": 61.1,
      "error": 61.1,
      "direction_correct": "False",
      "composite_score": 47.0,
      "fund_score": 40,
      "rate_regime": "falling",
      "rsi": 50.4,
      "vix": 25.8,
      "root_cause": "Model underestimated upside"
    },
    {
      "prediction_date": "2020-12-06",
      "predicted_90d": 7.0,
      "actual_90d": -6.5,
      "error": 13.5,
      "direction_correct": "False",
      "composite_score": 67.0,
      "fund_score": 40,
      "rate_regime": "stable",
      "rsi": 43.3,
      "vix": 21.3,
      "root_cause": "Model underestimated downside"
    },
    {
      "prediction_date": "2021-06-03",
      "predicted_90d": 3.0,
      "actual_90d": -11.1,
      "error": 14.1,
      "direction_correct": "False",
      "composite_score": 53.3,
      "fund_score": 53,
      "rate_regime": "stable",
      "rsi": 74.8,
      "vix": 18.0,
      "root_cause": "Model underestimated downside"
    },
    {
      "prediction_date": "2021-09-01",
      "predicted_90d": 5.0,
      "actual_90d": -21.7,
      "error": 26.7,
      "direction_correct": "False",
      "composite_score": 58.9,
      "fund_score": 53,
      "rate_regime": "stable",
      "rsi": 42.2,
      "vix": 16.1,
      "root_cause": "Model underestimated downside"
    },
    {
      "prediction_date": "2022-05-29",
      "predicted_90d": -4.0,
      "actual_90d": -19.9,
      "error": 15.9,
      "direction_correct": "True",
      "composite_score": 43.3,
      "fund_score": 26,
      "rate_regime": "rising",
      "rsi": 26.7,
      "vix": 27.5,
      "root_cause": "Model underestimated downside"
    },
    {
      "prediction_date": "2022-08-28",
      "predicted_90d": -8.0,
      "actual_90d": -26.8,
      "error": 18.8,
      "direction_correct": "True",
      "composite_score": 34.8,
      "fund_score": 26,
      "rate_regime": "rising",
      "rsi": 50.4,
      "vix": 21.8,
      "root_cause": "Model underestimated downside"
    },
    {
      "prediction_date": "2023-02-23",
      "predicted_90d": -4.0,
      "actual_90d": 56.6,
      "error": 60.6,
      "direction_correct": "False",
      "composite_score": 48.6,
      "fund_score": 32,
      "rate_regime": "rising",
      "rsi": 19.7,
      "vix": 21.1,
      "root_cause": "Model underestimated upside"
    },
    {
      "prediction_date": "2023-11-20",
      "predicted_90d": 3.0,
      "actual_90d": 38.9,
      "error": 35.9,
      "direction_correct": "True",
      "composite_score": 50.6,
      "fund_score": 32,
      "rate_regime": "stable",
      "rsi": 58.3,
      "vix": 13.4,
      "root_cause": "Model underestimated upside"
    },
    {
      "prediction_date": "2024-08-18",
      "predicted_90d": 1.0,
      "actual_90d": -20.8,
      "error": 21.8,
      "direction_correct": "False",
      "composite_score": 49.6,
      "fund_score": 22,
      "rate_regime": "stable",
      "rsi": 46.7,
      "vix": 15.2,
      "root_cause": "Model underestimated downside"
    },
    {
      "prediction_date": "2024-11-14",
      "predicted_90d": 0.0,
      "actual_90d": 28.3,
      "error": 28.3,
      "direction_correct": "False",
      "composite_score": 46.6,
      "fund_score": 22,
      "rate_regime": "falling",
      "rsi": 18.0,
      "vix": 14.3,
      "root_cause": "Model underestimated upside"
    },
    {
      "prediction_date": "2025-02-12",
      "predicted_90d": 0.0,
      "actual_90d": -22.0,
      "error": 22.0,
      "direction_correct": "True",
      "composite_score": 42.9,
      "fund_score": 65,
      "rate_regime": "falling",
      "rsi": 71.2,
      "vix": 15.9,
      "root_cause": "Model underestimated downside"
    },
    {
      "prediction_date": "2025-05-13",
      "predicted_90d": 5.0,
      "actual_90d": -29.2,
      "error": 34.2,
      "direction_correct": "False",
      "composite_score": 62.5,
      "fund_score": 65,
      "rate_regime": "stable",
      "rsi": 56.0,
      "vix": 18.2,
      "root_cause": "Model underestimated downside"
    },
    {
      "prediction_date": "2025-08-11",
      "predicted_90d": 7.0,
      "actual_90d": -18.2,
      "error": 25.2,
      "direction_correct": "False",
      "composite_score": 70.9,
      "fund_score": 65,
      "rate_regime": "stable",
      "rsi": 31.0,
      "vix": 16.2,
      "root_cause": "Model underestimated downside"
    },
    {
      "prediction_date": "2025-11-09",
      "predicted_90d": 9.0,
      "actual_90d": -4.1,
      "error": 13.1,
      "direction_correct": "False",
      "composite_score": 75.4,
      "fund_score": 65,
      "rate_regime": "stable",
      "rsi": 27.3,
      "vix": 19.5,
      "root_cause": "Model underestimated downside"
    }
  ]
}