{
  "mistakes": [
    {
      "prediction_date": "2016-09-27",
      "predicted_90d": 3.0,
      "actual_90d": 43.6,
      "error": 40.6,
      "direction_correct": "True",
      "composite_score": 57.5,
      "val_score": 40,
      "rate_regime": "stable",
      "rsi": 33.8,
      "pe_at_prediction": "P/E=20.3",
      "root_cause": "Model underestimated upside"
    },
    {
      "prediction_date": "2017-03-26",
      "predicted_90d": 3.0,
      "actual_90d": -14.2,
      "error": 17.2,
      "direction_correct": "False",
      "composite_score": 60.0,
      "val_score": 40,
      "rate_regime": "stable",
      "rsi": 27.1,
      "pe_at_prediction": "P/E=30.2",
      "root_cause": "Model underestimated downside"
    },
    {
      "prediction_date": "2017-06-25",
      "predicted_90d": 1.0,
      "actual_90d": -16.5,
      "error": 17.5,
      "direction_correct": "False",
      "composite_score": 46.2,
      "val_score": 40,
      "rate_regime": "stable",
      "rsi": 65.5,
      "pe_at_prediction": "P/E=28.5",
      "root_cause": "Model underestimated downside"
    },
    {
      "prediction_date": "2017-09-24",
      "predicted_90d": 3.0,
      "actual_90d": -9.9,
      "error": 12.9,
      "direction_correct": "False",
      "composite_score": 56.5,
      "val_score": 40,
      "rate_regime": "stable",
      "rsi": 67.1,
      "pe_at_prediction": "P/E=27.3",
      "root_cause": "Model underestimated downside"
    },
    {
      "prediction_date": "2018-03-21",
      "predicted_90d": 1.0,
      "actual_90d": -19.9,
      "error": 20.9,
      "direction_correct": "False",
      "composite_score": 47.9,
      "val_score": 40,
      "rate_regime": "stable",
      "rsi": 83.8,
      "pe_at_prediction": "P/E=26.4",
      "root_cause": "Model underestimated downside"
    },
    {
      "prediction_date": "2018-06-19",
      "predicted_90d": 5.5,
      "actual_90d": -32.4,
      "error": 37.9,
      "direction_correct": "False",
      "composite_score": 60.9,
      "val_score": 40,
      "rate_regime": "stable",
      "rsi": 25.2,
      "pe_at_prediction": "P/E=22.5",
      "root_cause": "Model underestimated downside"
    },
    {
      "prediction_date": "2018-09-17",
      "predicted_90d": 3.0,
      "actual_90d": -14.7,
      "error": 17.7,
      "direction_correct": "False",
      "composite_score": 58.0,
      "val_score": 46,
      "rate_regime": "stable",
      "rsi": 45.3,
      "pe_at_prediction": "P/E=17.9",
      "root_cause": "Model underestimated downside"
    },
    {
      "prediction_date": "2019-12-11",
      "predicted_90d": -4.5,
      "actual_90d": -23.8,
      "error": 19.3,
      "direction_correct": "True",
      "composite_score": 42.5,
      "val_score": 40,
      "rate_regime": "falling",
      "rsi": 53.4,
      "pe_at_prediction": "P/E=35.0",
      "root_cause": "Model underestimated downside"
    },
    {
      "prediction_date": "2020-03-10",
      "predicted_90d": 9.5,
      "actual_90d": -4.7,
      "error": 14.2,
      "direction_correct": "False",
      "composite_score": 81.1,
      "val_score": 50,
      "rate_regime": "stable",
      "rsi": 22.8,
      "pe_at_prediction": "P/E=N/A",
      "root_cause": "Model underestimated downside"
    },
    {
      "prediction_date": "2020-06-08",
      "predicted_90d": 0.0,
      "actual_90d": 45.5,
      "error": 45.5,
      "direction_correct": "False",
      "composite_score": 49.6,
      "val_score": 50,
      "rate_regime": "falling",
      "rsi": 84.4,
      "pe_at_prediction": "P/E=N/A",
      "root_cause": "Model underestimated upside"
    },
    {
      "prediction_date": "2020-09-06",
      "predicted_90d": 5.5,
      "actual_90d": -9.0,
      "error": 14.5,
      "direction_correct": "False",
      "composite_score": 60.1,
      "val_score": 50,
      "rate_regime": "stable",
      "rsi": 87.6,
      "pe_at_prediction": "P/E=N/A",
      "root_cause": "Model underestimated downside"
    },
    {
      "prediction_date": "2021-03-07",
      "predicted_90d": 3.0,
      "actual_90d": 20.5,
      "error": 17.5,
      "direction_correct": "True",
      "composite_score": 54.9,
      "val_score": 50,
      "rate_regime": "stable",
      "rsi": 74.1,
      "pe_at_prediction": "P/E=N/A",
      "root_cause": "Model underestimated upside"
    },
    {
      "prediction_date": "2022-02-28",
      "predicted_90d": 5.5,
      "actual_90d": -23.2,
      "error": 28.7,
      "direction_correct": "False",
      "composite_score": 65.2,
      "val_score": 50,
      "rate_regime": "stable",
      "rsi": 46.9,
      "pe_at_prediction": "P/E=N/A",
      "root_cause": "Model underestimated downside"
    },
    {
      "prediction_date": "2023-02-23",
      "predicted_90d": -2.0,
      "actual_90d": 23.9,
      "error": 25.9,
      "direction_correct": "False",
      "composite_score": 55.0,
      "val_score": 50,
      "rate_regime": "rising",
      "rsi": 14.4,
      "pe_at_prediction": "P/E=N/A",
      "root_cause": "Model underestimated upside"
    },
    {
      "prediction_date": "2023-05-24",
      "predicted_90d": -4.0,
      "actual_90d": -16.2,
      "error": 12.2,
      "direction_correct": "True",
      "composite_score": 47.0,
      "val_score": 50,
      "rate_regime": "rising",
      "rsi": 33.3,
      "pe_at_prediction": "P/E=N/A",
      "root_cause": "Model underestimated downside"
    },
    {
      "prediction_date": "2023-08-22",
      "predicted_90d": 5.5,
      "actual_90d": -14.7,
      "error": 20.2,
      "direction_correct": "False",
      "composite_score": 65.0,
      "val_score": 50,
      "rate_regime": "stable",
      "rsi": 52.4,
      "pe_at_prediction": "P/E=N/A",
      "root_cause": "Model underestimated downside"
    },
    {
      "prediction_date": "2024-02-18",
      "predicted_90d": 1.0,
      "actual_90d": -23.5,
      "error": 24.5,
      "direction_correct": "False",
      "composite_score": 50.2,
      "val_score": 50,
      "rate_regime": "stable",
      "rsi": 68.8,
      "pe_at_prediction": "P/E=N/A",
      "root_cause": "Model underestimated downside"
    },
    {
      "prediction_date": "2024-05-19",
      "predicted_90d": 5.5,
      "actual_90d": 24.9,
      "error": 19.4,
      "direction_correct": "True",
      "composite_score": 66.0,
      "val_score": 50,
      "rate_regime": "stable",
      "rsi": 10.8,
      "pe_at_prediction": "P/E=N/A",
      "root_cause": "Model underestimated upside"
    },
    {
      "prediction_date": "2024-11-14",
      "predicted_90d": 0.0,
      "actual_90d": -17.9,
      "error": 17.9,
      "direction_correct": "True",
      "composite_score": 53.0,
      "val_score": 50,
      "rate_regime": "falling",
      "rsi": 33.1,
      "pe_at_prediction": "P/E=N/A",
      "root_cause": "Model underestimated downside"
    },
    {
      "prediction_date": "2025-02-12",
      "predicted_90d": 2.0,
      "actual_90d": -21.0,
      "error": 23.0,
      "direction_correct": "False",
      "composite_score": 59.4,
      "val_score": 50,
      "rate_regime": "falling",
      "rsi": 23.1,
      "pe_at_prediction": "P/E=N/A",
      "root_cause": "Model underestimated downside"
    },
    {
      "prediction_date": "2025-05-13",
      "predicted_90d": 5.5,
      "actual_90d": -6.9,
      "error": 12.4,
      "direction_correct": "False",
      "composite_score": 65.6,
      "val_score": 50,
      "rate_regime": "stable",
      "rsi": 15.2,
      "pe_at_prediction": "P/E=N/A",
      "root_cause": "Model underestimated downside"
    },
    {
      "prediction_date": "2025-08-11",
      "predicted_90d": 5.5,
      "actual_90d": -11.9,
      "error": 17.4,
      "direction_correct": "False",
      "composite_score": 66.8,
      "val_score": 50,
      "rate_regime": "stable",
      "rsi": 29.6,
      "pe_at_prediction": "P/E=N/A",
      "root_cause": "Model underestimated downside"
    },
    {
      "prediction_date": "2025-11-09",
      "predicted_90d": 5.5,
      "actual_90d": -15.9,
      "error": 21.4,
      "direction_correct": "False",
      "composite_score": 66.8,
      "val_score": 50,
      "rate_regime": "stable",
      "rsi": 27.6,
      "pe_at_prediction": "P/E=N/A",
      "root_cause": "Model underestimated downside"
    }
  ]
}