{
  "sym": "4250",
  "name": "Jabal Omar Development",
  "generated": "2026-06-06T14:46:03.966405",
  "validation": {
    "n_predictions": 41,
    "directional_accuracy_pct": 34.1,
    "baseline_always_long_pct": 31.7,
    "edge_over_baseline_pct": 2.4,
    "mae_pct": 16.49,
    "avg_predicted_90d": 1.23,
    "avg_actual_90d": -1.75,
    "systematic_bias": -2.98,
    "sector_weights_applied": "Rate sensitive (mortgage demand). Oil via wealth effect.",
    "regime_breakdown": {
      "rising": {
        "n": 5,
        "accuracy": 60.0
      },
      "stable": {
        "n": 32,
        "accuracy": 31.2
      },
      "falling": {
        "n": 4,
        "accuracy": 25.0
      }
    }
  },
  "predictions": [
    {
      "prediction_date": "2016-01-03",
      "price": 55.32,
      "rate_regime": "stable",
      "sector": "Real Estate",
      "rsi": 70.9,
      "vix": 18.2,
      "pe_at_prediction": 151.8,
      "env_score": 60,
      "tech_score": 38,
      "fund_score": 40,
      "val_score": 40,
      "composite": 47.5,
      "base_30d_pct": 0.4,
      "base_60d_pct": 0.7,
      "base_90d_pct": 1.0,
      "confidence": 61,
      "actual_30d_pct": -17.7,
      "hit_target_30d": "False",
      "actual_60d_pct": -2.3,
      "hit_target_60d": "False",
      "actual_90d_pct": 10.2,
      "hit_target_90d": "True"
    },
    {
      "prediction_date": "2016-03-31",
      "price": 56.05,
      "rate_regime": "stable",
      "sector": "Real Estate",
      "rsi": 45.7,
      "vix": 13.9,
      "pe_at_prediction": 153.8,
      "env_score": 65,
      "tech_score": 50,
      "fund_score": 40,
      "val_score": 40,
      "composite": 52.5,
      "base_30d_pct": 0.4,
      "base_60d_pct": 0.7,
      "base_90d_pct": 1.0,
      "confidence": 63,
      "actual_30d_pct": 8.9,
      "hit_target_30d": "True",
      "actual_60d_pct": 12.0,
      "hit_target_60d": "True",
      "actual_90d_pct": 9.7,
      "hit_target_90d": "True"
    },
    {
      "prediction_date": "2016-06-29",
      "price": 63.25,
      "rate_regime": "stable",
      "sector": "Real Estate",
      "rsi": 58.9,
      "vix": 16.6,
      "pe_at_prediction": 173.6,
      "env_score": 78,
      "tech_score": 40,
      "fund_score": 40,
      "val_score": 40,
      "composite": 55.2,
      "base_30d_pct": 1.2,
      "base_60d_pct": 2.1,
      "base_90d_pct": 3.0,
      "confidence": 59,
      "actual_30d_pct": -1.2,
      "hit_target_30d": "False",
      "actual_60d_pct": -17.8,
      "hit_target_60d": "False",
      "actual_90d_pct": 9.5,
      "hit_target_90d": "True"
    },
    {
      "prediction_date": "2016-09-27",
      "price": 53.75,
      "rate_regime": "stable",
      "sector": "Real Estate",
      "rsi": 3.3,
      "vix": 13.1,
      "pe_at_prediction": 147.5,
      "env_score": 65,
      "tech_score": 98,
      "fund_score": 40,
      "val_score": 40,
      "composite": 64.5,
      "base_30d_pct": 2.2,
      "base_60d_pct": 3.8,
      "base_90d_pct": 5.5,
      "confidence": 66,
      "actual_30d_pct": 24.7,
      "hit_target_30d": "True",
      "actual_60d_pct": 39.5,
      "hit_target_60d": "True",
      "actual_90d_pct": 29.8,
      "hit_target_90d": "True"
    },
    {
      "prediction_date": "2016-12-27",
      "price": 74.75,
      "rate_regime": "stable",
      "sector": "Real Estate",
      "rsi": 44.4,
      "vix": 12.0,
      "pe_at_prediction": null,
      "env_score": 75,
      "tech_score": 60,
      "fund_score": 40,
      "val_score": 50,
      "composite": 60.5,
      "base_30d_pct": 2.2,
      "base_60d_pct": 3.8,
      "base_90d_pct": 5.5,
      "confidence": 68,
      "actual_30d_pct": -8.4,
      "hit_target_30d": "False",
      "actual_60d_pct": -9.7,
      "hit_target_60d": "False",
      "actual_90d_pct": -10.4,
      "hit_target_90d": "False"
    },
    {
      "prediction_date": "2017-03-26",
      "price": 69.25,
      "rate_regime": "stable",
      "sector": "Real Estate",
      "rsi": 66.7,
      "vix": 13.1,
      "pe_at_prediction": 74.9,
      "env_score": 65,
      "tech_score": 50,
      "fund_score": 73,
      "val_score": 40,
      "composite": 59.1,
      "base_30d_pct": 1.2,
      "base_60d_pct": 2.1,
      "base_90d_pct": 3.0,
      "confidence": 67,
      "actual_30d_pct": -1.8,
      "hit_target_30d": "False",
      "actual_60d_pct": 6.9,
      "hit_target_60d": "True",
      "actual_90d_pct": -2.4,
      "hit_target_90d": "False"
    },
    {
      "prediction_date": "2017-06-25",
      "price": 74.0,
      "rate_regime": "stable",
      "sector": "Real Estate",
      "rsi": 70.8,
      "vix": 10.5,
      "pe_at_prediction": 80.1,
      "env_score": 57,
      "tech_score": 23,
      "fund_score": 73,
      "val_score": 40,
      "composite": 49.2,
      "base_30d_pct": 0.4,
      "base_60d_pct": 0.7,
      "base_90d_pct": 1.0,
      "confidence": 57,
      "actual_30d_pct": -9.1,
      "hit_target_30d": "False",
      "actual_60d_pct": -9.5,
      "hit_target_60d": "False",
      "actual_90d_pct": -16.9,
      "hit_target_90d": "False"
    },
    {
      "prediction_date": "2017-09-24",
      "price": 66.2,
      "rate_regime": "stable",
      "sector": "Real Estate",
      "rsi": 28.6,
      "vix": 9.7,
      "pe_at_prediction": 71.6,
      "env_score": 75,
      "tech_score": 75,
      "fund_score": 73,
      "val_score": 40,
      "composite": 69.3,
      "base_30d_pct": 3.0,
      "base_60d_pct": 5.2,
      "base_90d_pct": 7.5,
      "confidence": 78,
      "actual_30d_pct": -6.5,
      "hit_target_30d": "False",
      "actual_60d_pct": -10.3,
      "hit_target_60d": "False",
      "actual_90d_pct": -10.0,
      "hit_target_90d": "False"
    },
    {
      "prediction_date": "2017-12-21",
      "price": 59.8,
      "rate_regime": "stable",
      "sector": "Real Estate",
      "rsi": 54.5,
      "vix": 9.6,
      "pe_at_prediction": 64.7,
      "env_score": 65,
      "tech_score": 50,
      "fund_score": 73,
      "val_score": 40,
      "composite": 59.1,
      "base_30d_pct": 1.2,
      "base_60d_pct": 2.1,
      "base_90d_pct": 3.0,
      "confidence": 67,
      "actual_30d_pct": 1.0,
      "hit_target_30d": "True",
      "actual_60d_pct": -14.5,
      "hit_target_60d": "False",
      "actual_90d_pct": -21.4,
      "hit_target_90d": "False"
    },
    {
      "prediction_date": "2018-03-21",
      "price": 50.2,
      "rate_regime": "stable",
      "sector": "Real Estate",
      "rsi": 36.2,
      "vix": 17.9,
      "pe_at_prediction": 113.4,
      "env_score": 68,
      "tech_score": 58,
      "fund_score": 44,
      "val_score": 40,
      "composite": 56.5,
      "base_30d_pct": 1.2,
      "base_60d_pct": 2.1,
      "base_90d_pct": 3.0,
      "confidence": 67,
      "actual_30d_pct": -5.0,
      "hit_target_30d": "False",
      "actual_60d_pct": -20.3,
      "hit_target_60d": "False",
      "actual_90d_pct": -16.9,
      "hit_target_90d": "False"
    },
    {
      "prediction_date": "2018-06-19",
      "price": 40.0,
      "rate_regime": "stable",
      "sector": "Real Estate",
      "rsi": 67.5,
      "vix": 13.4,
      "pe_at_prediction": 90.4,
      "env_score": 65,
      "tech_score": 50,
      "fund_score": 44,
      "val_score": 40,
      "composite": 53.3,
      "base_30d_pct": 1.2,
      "base_60d_pct": 2.1,
      "base_90d_pct": 3.0,
      "confidence": 63,
      "actual_30d_pct": 2.5,
      "hit_target_30d": "True",
      "actual_60d_pct": -10.0,
      "hit_target_60d": "False",
      "actual_90d_pct": -12.5,
      "hit_target_90d": "False"
    },
    {
      "prediction_date": "2018-09-17",
      "price": 38.2,
      "rate_regime": "stable",
      "sector": "Real Estate",
      "rsi": 59.8,
      "vix": 13.7,
      "pe_at_prediction": 86.3,
      "env_score": 65,
      "tech_score": 50,
      "fund_score": 44,
      "val_score": 40,
      "composite": 53.3,
      "base_30d_pct": 1.2,
      "base_60d_pct": 2.1,
      "base_90d_pct": 3.0,
      "confidence": 63,
      "actual_30d_pct": -6.0,
      "hit_target_30d": "False",
      "actual_60d_pct": -8.1,
      "hit_target_60d": "False",
      "actual_90d_pct": -14.9,
      "hit_target_90d": "False"
    },
    {
      "prediction_date": "2018-12-16",
      "price": 36.7,
      "rate_regime": "stable",
      "sector": "Real Estate",
      "rsi": 73.0,
      "vix": 20.6,
      "pe_at_prediction": 82.9,
      "env_score": 63,
      "tech_score": 23,
      "fund_score": 44,
      "val_score": 40,
      "composite": 45.8,
      "base_30d_pct": -1.4,
      "base_60d_pct": -2.4,
      "base_90d_pct": -3.5,
      "confidence": 57,
      "actual_30d_pct": -8.3,
      "hit_target_30d": "True",
      "actual_60d_pct": -8.2,
      "hit_target_60d": "True",
      "actual_90d_pct": -10.6,
      "hit_target_90d": "True"
    },
    {
      "prediction_date": "2019-03-17",
      "price": 32.5,
      "rate_regime": "stable",
      "sector": "Real Estate",
      "rsi": 41.2,
      "vix": 13.5,
      "pe_at_prediction": 130.4,
      "env_score": 75,
      "tech_score": 60,
      "fund_score": 30,
      "val_score": 40,
      "composite": 57.0,
      "base_30d_pct": 1.2,
      "base_60d_pct": 2.1,
      "base_90d_pct": 3.0,
      "confidence": 66,
      "actual_30d_pct": -2.2,
      "hit_target_30d": "False",
      "actual_60d_pct": -12.0,
      "hit_target_60d": "False",
      "actual_90d_pct": -12.0,
      "hit_target_90d": "False"
    },
    {
      "prediction_date": "2019-06-16",
      "price": 28.9,
      "rate_regime": "stable",
      "sector": "Real Estate",
      "rsi": 91.4,
      "vix": 15.8,
      "pe_at_prediction": 116.0,
      "env_score": 68,
      "tech_score": 30,
      "fund_score": 30,
      "val_score": 40,
      "composite": 46.7,
      "base_30d_pct": 0.4,
      "base_60d_pct": 0.7,
      "base_90d_pct": 1.0,
      "confidence": 57,
      "actual_30d_pct": 0.7,
      "hit_target_30d": "True",
      "actual_60d_pct": -10.4,
      "hit_target_60d": "False",
      "actual_90d_pct": -4.5,
      "hit_target_90d": "False"
    },
    {
      "prediction_date": "2019-09-12",
      "price": 25.35,
      "rate_regime": "stable",
      "sector": "Real Estate",
      "rsi": 44.6,
      "vix": 14.2,
      "pe_at_prediction": 101.7,
      "env_score": 65,
      "tech_score": 50,
      "fund_score": 30,
      "val_score": 40,
      "composite": 50.5,
      "base_30d_pct": 0.4,
      "base_60d_pct": 0.7,
      "base_90d_pct": 1.0,
      "confidence": 61,
      "actual_30d_pct": 9.3,
      "hit_target_30d": "True",
      "actual_60d_pct": -5.0,
      "hit_target_60d": "False",
      "actual_90d_pct": 4.1,
      "hit_target_90d": "True"
    },
    {
      "prediction_date": "2019-12-11",
      "price": 23.96,
      "rate_regime": "falling",
      "sector": "Real Estate",
      "rsi": 50.8,
      "vix": 15.0,
      "pe_at_prediction": 96.1,
      "env_score": 52,
      "tech_score": 50,
      "fund_score": 30,
      "val_score": 40,
      "composite": 45.3,
      "base_30d_pct": -1.8,
      "base_60d_pct": -3.1,
      "base_90d_pct": -4.5,
      "confidence": 67,
      "actual_30d_pct": 13.1,
      "hit_target_30d": "False",
      "actual_60d_pct": 24.4,
      "hit_target_60d": "False",
      "actual_90d_pct": 1.9,
      "hit_target_90d": "False"
    },
    {
      "prediction_date": "2020-03-10",
      "price": 24.94,
      "rate_regime": "stable",
      "sector": "Real Estate",
      "rsi": 45.2,
      "vix": 47.3,
      "pe_at_prediction": null,
      "env_score": 68,
      "tech_score": 50,
      "fund_score": 40,
      "val_score": 50,
      "composite": 55.2,
      "base_30d_pct": 1.2,
      "base_60d_pct": 2.1,
      "base_90d_pct": 3.0,
      "confidence": 64,
      "actual_30d_pct": -4.1,
      "hit_target_30d": "False",
      "actual_60d_pct": -9.7,
      "hit_target_60d": "False",
      "actual_90d_pct": 11.1,
      "hit_target_90d": "True"
    },
    {
      "prediction_date": "2020-06-08",
      "price": 22.78,
      "rate_regime": "falling",
      "sector": "Real Estate",
      "rsi": 50.4,
      "vix": 25.8,
      "pe_at_prediction": null,
      "env_score": 50,
      "tech_score": 50,
      "fund_score": 40,
      "val_score": 50,
      "composite": 48.0,
      "base_30d_pct": 0.0,
      "base_60d_pct": 0.0,
      "base_90d_pct": 0.0,
      "confidence": 66,
      "actual_30d_pct": 19.0,
      "hit_target_30d": "False",
      "actual_60d_pct": 47.1,
      "hit_target_60d": "False",
      "actual_90d_pct": 61.1,
      "hit_target_90d": "False"
    },
    {
      "prediction_date": "2020-09-06",
      "price": 31.8,
      "rate_regime": "stable",
      "sector": "Real Estate",
      "rsi": 78.2,
      "vix": 33.6,
      "pe_at_prediction": null,
      "env_score": 86,
      "tech_score": 3,
      "fund_score": 40,
      "val_score": 50,
      "composite": 50.6,
      "base_30d_pct": 0.4,
      "base_60d_pct": 0.7,
      "base_90d_pct": 1.0,
      "confidence": 44,
      "actual_30d_pct": 11.6,
      "hit_target_30d": "True",
      "actual_60d_pct": 3.0,
      "hit_target_60d": "True",
      "actual_90d_pct": -7.2,
      "hit_target_90d": "False"
    },
    {
      "prediction_date": "2020-12-06",
      "price": 31.0,
      "rate_regime": "stable",
      "sector": "Real Estate",
      "rsi": 43.3,
      "vix": 21.3,
      "pe_at_prediction": null,
      "env_score": 81,
      "tech_score": 70,
      "fund_score": 40,
      "val_score": 50,
      "composite": 65.4,
      "base_30d_pct": 2.2,
      "base_60d_pct": 3.8,
      "base_90d_pct": 5.5,
      "confidence": 73,
      "actual_30d_pct": -6.5,
      "hit_target_30d": "False",
      "actual_60d_pct": -9.8,
      "hit_target_60d": "False",
      "actual_90d_pct": -6.5,
      "hit_target_90d": "False"
    },
    {
      "prediction_date": "2021-03-07",
      "price": 29.9,
      "rate_regime": "stable",
      "sector": "Real Estate",
      "rsi": 71.0,
      "vix": 28.6,
      "pe_at_prediction": null,
      "env_score": 81,
      "tech_score": 23,
      "fund_score": 53,
      "val_score": 50,
      "composite": 56.2,
      "base_30d_pct": 1.2,
      "base_60d_pct": 2.1,
      "base_90d_pct": 3.0,
      "confidence": 54,
      "actual_30d_pct": -2.8,
      "hit_target_30d": "False",
      "actual_60d_pct": 16.2,
      "hit_target_60d": "True",
      "actual_90d_pct": 13.4,
      "hit_target_90d": "True"
    },
    {
      "prediction_date": "2021-06-03",
      "price": 34.75,
      "rate_regime": "stable",
      "sector": "Real Estate",
      "rsi": 74.8,
      "vix": 18.0,
      "pe_at_prediction": null,
      "env_score": 78,
      "tech_score": 18,
      "fund_score": 53,
      "val_score": 50,
      "composite": 53.8,
      "base_30d_pct": 1.2,
      "base_60d_pct": 2.1,
      "base_90d_pct": 3.0,
      "confidence": 52,
      "actual_30d_pct": -2.4,
      "hit_target_30d": "False",
      "actual_60d_pct": -4.3,
      "hit_target_60d": "False",
      "actual_90d_pct": -11.1,
      "hit_target_90d": "False"
    },
    {
      "prediction_date": "2021-09-01",
      "price": 32.9,
      "rate_regime": "stable",
      "sector": "Real Estate",
      "rsi": 42.2,
      "vix": 16.1,
      "pe_at_prediction": null,
      "env_score": 68,
      "tech_score": 50,
      "fund_score": 53,
      "val_score": 50,
      "composite": 57.8,
      "base_30d_pct": 1.2,
      "base_60d_pct": 2.1,
      "base_90d_pct": 3.0,
      "confidence": 65,
      "actual_30d_pct": -11.2,
      "hit_target_30d": "False",
      "actual_60d_pct": -9.7,
      "hit_target_60d": "False",
      "actual_90d_pct": -21.7,
      "hit_target_90d": "False"
    },
    {
      "prediction_date": "2021-11-30",
      "price": 27.5,
      "rate_regime": "stable",
      "sector": "Real Estate",
      "rsi": 28.9,
      "vix": 27.2,
      "pe_at_prediction": null,
      "env_score": 71,
      "tech_score": 93,
      "fund_score": 53,
      "val_score": 50,
      "composite": 69.8,
      "base_30d_pct": 3.0,
      "base_60d_pct": 5.2,
      "base_90d_pct": 7.5,
      "confidence": 73,
      "actual_30d_pct": -6.5,
      "hit_target_30d": "False",
      "actual_60d_pct": -14.3,
      "hit_target_60d": "False",
      "actual_90d_pct": -1.8,
      "hit_target_90d": "False"
    },
    {
      "prediction_date": "2022-02-28",
      "price": 24.7,
      "rate_regime": "stable",
      "sector": "Real Estate",
      "rsi": 44.9,
      "vix": 30.1,
      "pe_at_prediction": null,
      "env_score": 86,
      "tech_score": 50,
      "fund_score": 26,
      "val_score": 50,
      "composite": 59.6,
      "base_30d_pct": 1.2,
      "base_60d_pct": 2.1,
      "base_90d_pct": 3.0,
      "confidence": 62,
      "actual_30d_pct": 18.2,
      "hit_target_30d": "True",
      "actual_60d_pct": 8.9,
      "hit_target_60d": "True",
      "actual_90d_pct": -4.5,
      "hit_target_90d": "False"
    },
    {
      "prediction_date": "2022-05-29",
      "price": 26.1,
      "rate_regime": "rising",
      "sector": "Real Estate",
      "rsi": 26.7,
      "vix": 27.5,
      "pe_at_prediction": null,
      "env_score": 41,
      "tech_score": 65,
      "fund_score": 26,
      "val_score": 50,
      "composite": 45.4,
      "base_30d_pct": -3.4,
      "base_60d_pct": -5.9,
      "base_90d_pct": -8.5,
      "confidence": 62,
      "actual_30d_pct": -11.7,
      "hit_target_30d": "True",
      "actual_60d_pct": -11.6,
      "hit_target_60d": "True",
      "actual_90d_pct": -19.9,
      "hit_target_90d": "True"
    },
    {
      "prediction_date": "2022-08-28",
      "price": 23.4,
      "rate_regime": "rising",
      "sector": "Real Estate",
      "rsi": 50.4,
      "vix": 21.8,
      "pe_at_prediction": null,
      "env_score": 23,
      "tech_score": 50,
      "fund_score": 26,
      "val_score": 50,
      "composite": 34.4,
      "base_30d_pct": -3.4,
      "base_60d_pct": -5.9,
      "base_90d_pct": -8.5,
      "confidence": 69,
      "actual_30d_pct": -8.8,
      "hit_target_30d": "True",
      "actual_60d_pct": -12.7,
      "hit_target_60d": "True",
      "actual_90d_pct": -26.8,
      "hit_target_90d": "True"
    },
    {
      "prediction_date": "2022-11-27",
      "price": 19.4,
      "rate_regime": "rising",
      "sector": "Real Estate",
      "rsi": 30.2,
      "vix": 21.3,
      "pe_at_prediction": null,
      "env_score": 23,
      "tech_score": 86,
      "fund_score": 26,
      "val_score": 50,
      "composite": 43.4,
      "base_30d_pct": -3.4,
      "base_60d_pct": -5.9,
      "base_90d_pct": -8.5,
      "confidence": 53,
      "actual_30d_pct": -9.4,
      "hit_target_30d": "True",
      "actual_60d_pct": -5.7,
      "hit_target_60d": "True",
      "actual_90d_pct": 3.8,
      "hit_target_90d": "False"
    },
    {
      "prediction_date": "2023-02-23",
      "price": 17.3,
      "rate_regime": "rising",
      "sector": "Real Estate",
      "rsi": 19.7,
      "vix": 21.1,
      "pe_at_prediction": null,
      "env_score": 31,
      "tech_score": 90,
      "fund_score": 32,
      "val_score": 50,
      "composite": 48.8,
      "base_30d_pct": -1.6,
      "base_60d_pct": -2.8,
      "base_90d_pct": -4.0,
      "confidence": 51,
      "actual_30d_pct": 22.5,
      "hit_target_30d": "False",
      "actual_60d_pct": 44.5,
      "hit_target_60d": "False",
      "actual_90d_pct": 56.6,
      "hit_target_90d": "False"
    },
    {
      "prediction_date": "2023-05-24",
      "price": 24.02,
      "rate_regime": "rising",
      "sector": "Real Estate",
      "rsi": 68.0,
      "vix": 20.0,
      "pe_at_prediction": null,
      "env_score": 31,
      "tech_score": 50,
      "fund_score": 32,
      "val_score": 50,
      "composite": 38.8,
      "base_30d_pct": -3.4,
      "base_60d_pct": -5.9,
      "base_90d_pct": -8.5,
      "confidence": 68,
      "actual_30d_pct": 11.2,
      "hit_target_30d": "False",
      "actual_60d_pct": -5.3,
      "hit_target_60d": "True",
      "actual_90d_pct": -8.7,
      "hit_target_90d": "True"
    },
    {
      "prediction_date": "2023-08-22",
      "price": 23.08,
      "rate_regime": "stable",
      "sector": "Real Estate",
      "rsi": 17.0,
      "vix": 17.0,
      "pe_at_prediction": null,
      "env_score": 78,
      "tech_score": 95,
      "fund_score": 32,
      "val_score": 50,
      "composite": 68.8,
      "base_30d_pct": 3.0,
      "base_60d_pct": 5.2,
      "base_90d_pct": 7.5,
      "confidence": 73,
      "actual_30d_pct": -3.8,
      "hit_target_30d": "False",
      "actual_60d_pct": -15.3,
      "hit_target_60d": "False",
      "actual_90d_pct": -4.4,
      "hit_target_90d": "False"
    },
    {
      "prediction_date": "2023-11-20",
      "price": 21.64,
      "rate_regime": "stable",
      "sector": "Real Estate",
      "rsi": 58.3,
      "vix": 13.4,
      "pe_at_prediction": null,
      "env_score": 65,
      "tech_score": 50,
      "fund_score": 32,
      "val_score": 50,
      "composite": 52.4,
      "base_30d_pct": 0.4,
      "base_60d_pct": 0.7,
      "base_90d_pct": 1.0,
      "confidence": 62,
      "actual_30d_pct": 3.5,
      "hit_target_30d": "True",
      "actual_60d_pct": 19.9,
      "hit_target_60d": "True",
      "actual_90d_pct": 38.9,
      "hit_target_90d": "True"
    },
    {
      "prediction_date": "2024-02-18",
      "price": 26.95,
      "rate_regime": "stable",
      "sector": "Real Estate",
      "rsi": 84.4,
      "vix": 14.0,
      "pe_at_prediction": null,
      "env_score": 65,
      "tech_score": 0,
      "fund_score": 22,
      "val_score": 50,
      "composite": 37.9,
      "base_30d_pct": -1.4,
      "base_60d_pct": -2.4,
      "base_90d_pct": -3.5,
      "confidence": 57,
      "actual_30d_pct": 4.5,
      "hit_target_30d": "False",
      "actual_60d_pct": -7.2,
      "hit_target_60d": "True",
      "actual_90d_pct": -10.7,
      "hit_target_90d": "True"
    },
    {
      "prediction_date": "2024-05-19",
      "price": 24.92,
      "rate_regime": "stable",
      "sector": "Real Estate",
      "rsi": 18.3,
      "vix": 12.4,
      "pe_at_prediction": null,
      "env_score": 65,
      "tech_score": 100,
      "fund_score": 22,
      "val_score": 50,
      "composite": 62.9,
      "base_30d_pct": 2.2,
      "base_60d_pct": 3.8,
      "base_90d_pct": 5.5,
      "confidence": 65,
      "actual_30d_pct": -7.1,
      "hit_target_30d": "False",
      "actual_60d_pct": 4.5,
      "hit_target_60d": "True",
      "actual_90d_pct": 0.0,
      "hit_target_90d": "False"
    },
    {
      "prediction_date": "2024-08-18",
      "price": 26.05,
      "rate_regime": "stable",
      "sector": "Real Estate",
      "rsi": 46.7,
      "vix": 15.2,
      "pe_at_prediction": null,
      "env_score": 68,
      "tech_score": 50,
      "fund_score": 22,
      "val_score": 50,
      "composite": 51.6,
      "base_30d_pct": 0.4,
      "base_60d_pct": 0.7,
      "base_90d_pct": 1.0,
      "confidence": 61,
      "actual_30d_pct": -4.3,
      "hit_target_30d": "False",
      "actual_60d_pct": -18.4,
      "hit_target_60d": "False",
      "actual_90d_pct": -20.8,
      "hit_target_90d": "False"
    },
    {
      "prediction_date": "2024-11-14",
      "price": 20.38,
      "rate_regime": "falling",
      "sector": "Real Estate",
      "rsi": 18.0,
      "vix": 14.3,
      "pe_at_prediction": null,
      "env_score": 44,
      "tech_score": 80,
      "fund_score": 22,
      "val_score": 50,
      "composite": 49.5,
      "base_30d_pct": 0.0,
      "base_60d_pct": 0.0,
      "base_90d_pct": 0.0,
      "confidence": 56,
      "actual_30d_pct": -0.1,
      "hit_target_30d": "True",
      "actual_60d_pct": 27.1,
      "hit_target_60d": "False",
      "actual_90d_pct": 28.3,
      "hit_target_90d": "False"
    },
    {
      "prediction_date": "2025-02-12",
      "price": 25.6,
      "rate_regime": "falling",
      "sector": "Real Estate",
      "rsi": 71.2,
      "vix": 15.9,
      "pe_at_prediction": 36.3,
      "env_score": 55,
      "tech_score": 18,
      "fund_score": 65,
      "val_score": 40,
      "composite": 45.5,
      "base_30d_pct": -1.8,
      "base_60d_pct": -3.1,
      "base_90d_pct": -4.5,
      "confidence": 58,
      "actual_30d_pct": 1.8,
      "hit_target_30d": "False",
      "actual_60d_pct": -2.7,
      "hit_target_60d": "True",
      "actual_90d_pct": -22.0,
      "hit_target_90d": "True"
    },
    {
      "prediction_date": "2025-05-13",
      "price": 25.4,
      "rate_regime": "stable",
      "sector": "Real Estate",
      "rsi": 56.0,
      "vix": 18.2,
      "pe_at_prediction": 36.1,
      "env_score": 60,
      "tech_score": 50,
      "fund_score": 65,
      "val_score": 40,
      "composite": 55.5,
      "base_30d_pct": 1.2,
      "base_60d_pct": 2.1,
      "base_90d_pct": 3.0,
      "confidence": 66,
      "actual_30d_pct": -20.8,
      "hit_target_30d": "False",
      "actual_60d_pct": -27.1,
      "hit_target_60d": "False",
      "actual_90d_pct": -29.2,
      "hit_target_90d": "False"
    },
    {
      "prediction_date": "2025-08-11",
      "price": 18.51,
      "rate_regime": "stable",
      "sector": "Real Estate",
      "rsi": 31.0,
      "vix": 16.2,
      "pe_at_prediction": 19.1,
      "env_score": 68,
      "tech_score": 78,
      "fund_score": 65,
      "val_score": 40,
      "composite": 65.7,
      "base_30d_pct": 2.2,
      "base_60d_pct": 3.8,
      "base_90d_pct": 5.5,
      "confidence": 73,
      "actual_30d_pct": -2.9,
      "hit_target_30d": "False",
      "actual_60d_pct": -8.3,
      "hit_target_60d": "False",
      "actual_90d_pct": -18.2,
      "hit_target_90d": "False"
    },
    {
      "prediction_date": "2025-11-09",
      "price": 16.22,
      "rate_regime": "stable",
      "sector": "Real Estate",
      "rsi": 27.3,
      "vix": 19.5,
      "pe_at_prediction": 17.3,
      "env_score": 68,
      "tech_score": 93,
      "fund_score": 65,
      "val_score": 46,
      "composite": 70.4,
      "base_30d_pct": 3.0,
      "base_60d_pct": 5.2,
      "base_90d_pct": 7.5,
      "confidence": 72,
      "actual_30d_pct": -5.5,
      "hit_target_30d": "False",
      "actual_60d_pct": -0.7,
      "hit_target_60d": "False",
      "actual_90d_pct": -4.1,
      "hit_target_90d": "False"
    },
    {
      "prediction_date": "2026-02-08",
      "price": 16.19,
      "rate_regime": "stable",
      "sector": "Real Estate",
      "rsi": 51.8,
      "vix": 21.8,
      "pe_at_prediction": 5.8,
      "env_score": 71,
      "tech_score": 40,
      "fund_score": 65,
      "val_score": 65,
      "composite": 61.2,
      "base_30d_pct": 2.2,
      "base_60d_pct": 3.8,
      "base_90d_pct": 5.5,
      "confidence": 65,
      "actual_30d_pct": -2.5,
      "hit_target_30d": "False",
      "actual_60d_pct": -8.6,
      "hit_target_60d": "False"
    }
  ],
  "mistake_vault": [
    {
      "prediction_date": "2016-09-27",
      "predicted_90d": 5.5,
      "actual_90d": 29.8,
      "error": 24.3,
      "direction_correct": "True",
      "composite_score": 64.5,
      "sector": "Real Estate",
      "rate_regime": "stable",
      "root_cause": "Model underestimated upside"
    },
    {
      "prediction_date": "2016-12-27",
      "predicted_90d": 5.5,
      "actual_90d": -10.4,
      "error": 15.9,
      "direction_correct": "False",
      "composite_score": 60.5,
      "sector": "Real Estate",
      "rate_regime": "stable",
      "root_cause": "Sector weights may need tuning for Real Estate"
    },
    {
      "prediction_date": "2017-06-25",
      "predicted_90d": 1.0,
      "actual_90d": -16.9,
      "error": 17.9,
      "direction_correct": "False",
      "composite_score": 49.2,
      "sector": "Real Estate",
      "rate_regime": "stable",
      "root_cause": "Model underestimated downside"
    },
    {
      "prediction_date": "2017-09-24",
      "predicted_90d": 7.5,
      "actual_90d": -10.0,
      "error": 17.5,
      "direction_correct": "False",
      "composite_score": 69.3,
      "sector": "Real Estate",
      "rate_regime": "stable",
      "root_cause": "Sector weights may need tuning for Real Estate"
    },
    {
      "prediction_date": "2017-12-21",
      "predicted_90d": 3.0,
      "actual_90d": -21.4,
      "error": 24.4,
      "direction_correct": "False",
      "composite_score": 59.1,
      "sector": "Real Estate",
      "rate_regime": "stable",
      "root_cause": "Model underestimated downside"
    },
    {
      "prediction_date": "2018-03-21",
      "predicted_90d": 3.0,
      "actual_90d": -16.9,
      "error": 19.9,
      "direction_correct": "False",
      "composite_score": 56.5,
      "sector": "Real Estate",
      "rate_regime": "stable",
      "root_cause": "Model underestimated downside"
    },
    {
      "prediction_date": "2018-06-19",
      "predicted_90d": 3.0,
      "actual_90d": -12.5,
      "error": 15.5,
      "direction_correct": "False",
      "composite_score": 53.3,
      "sector": "Real Estate",
      "rate_regime": "stable",
      "root_cause": "Model underestimated downside"
    },
    {
      "prediction_date": "2018-09-17",
      "predicted_90d": 3.0,
      "actual_90d": -14.9,
      "error": 17.9,
      "direction_correct": "False",
      "composite_score": 53.3,
      "sector": "Real Estate",
      "rate_regime": "stable",
      "root_cause": "Model underestimated downside"
    },
    {
      "prediction_date": "2019-03-17",
      "predicted_90d": 3.0,
      "actual_90d": -12.0,
      "error": 15.0,
      "direction_correct": "False",
      "composite_score": 57.0,
      "sector": "Real Estate",
      "rate_regime": "stable",
      "root_cause": "Sector weights may need tuning for Real Estate"
    },
    {
      "prediction_date": "2020-06-08",
      "predicted_90d": 0.0,
      "actual_90d": 61.1,
      "error": 61.1,
      "direction_correct": "False",
      "composite_score": 48.0,
      "sector": "Real Estate",
      "rate_regime": "falling",
      "root_cause": "Model underestimated upside"
    },
    {
      "prediction_date": "2021-06-03",
      "predicted_90d": 3.0,
      "actual_90d": -11.1,
      "error": 14.1,
      "direction_correct": "False",
      "composite_score": 53.8,
      "sector": "Real Estate",
      "rate_regime": "stable",
      "root_cause": "Sector weights may need tuning for Real Estate"
    },
    {
      "prediction_date": "2021-09-01",
      "predicted_90d": 3.0,
      "actual_90d": -21.7,
      "error": 24.7,
      "direction_correct": "False",
      "composite_score": 57.8,
      "sector": "Real Estate",
      "rate_regime": "stable",
      "root_cause": "Model underestimated downside"
    },
    {
      "prediction_date": "2022-08-28",
      "predicted_90d": -8.5,
      "actual_90d": -26.8,
      "error": 18.3,
      "direction_correct": "True",
      "composite_score": 34.4,
      "sector": "Real Estate",
      "rate_regime": "rising",
      "root_cause": "Model underestimated downside"
    },
    {
      "prediction_date": "2022-11-27",
      "predicted_90d": -8.5,
      "actual_90d": 3.8,
      "error": 12.3,
      "direction_correct": "False",
      "composite_score": 43.4,
      "sector": "Real Estate",
      "rate_regime": "rising",
      "root_cause": "Sector weights may need tuning for Real Estate"
    },
    {
      "prediction_date": "2023-02-23",
      "predicted_90d": -4.0,
      "actual_90d": 56.6,
      "error": 60.6,
      "direction_correct": "False",
      "composite_score": 48.8,
      "sector": "Real Estate",
      "rate_regime": "rising",
      "root_cause": "Model underestimated upside"
    },
    {
      "prediction_date": "2023-11-20",
      "predicted_90d": 1.0,
      "actual_90d": 38.9,
      "error": 37.9,
      "direction_correct": "True",
      "composite_score": 52.4,
      "sector": "Real Estate",
      "rate_regime": "stable",
      "root_cause": "Model underestimated upside"
    },
    {
      "prediction_date": "2024-08-18",
      "predicted_90d": 1.0,
      "actual_90d": -20.8,
      "error": 21.8,
      "direction_correct": "False",
      "composite_score": 51.6,
      "sector": "Real Estate",
      "rate_regime": "stable",
      "root_cause": "Model underestimated downside"
    },
    {
      "prediction_date": "2024-11-14",
      "predicted_90d": 0.0,
      "actual_90d": 28.3,
      "error": 28.3,
      "direction_correct": "False",
      "composite_score": 49.5,
      "sector": "Real Estate",
      "rate_regime": "falling",
      "root_cause": "Model underestimated upside"
    },
    {
      "prediction_date": "2025-02-12",
      "predicted_90d": -4.5,
      "actual_90d": -22.0,
      "error": 17.5,
      "direction_correct": "True",
      "composite_score": 45.5,
      "sector": "Real Estate",
      "rate_regime": "falling",
      "root_cause": "Model underestimated downside"
    },
    {
      "prediction_date": "2025-05-13",
      "predicted_90d": 3.0,
      "actual_90d": -29.2,
      "error": 32.2,
      "direction_correct": "False",
      "composite_score": 55.5,
      "sector": "Real Estate",
      "rate_regime": "stable",
      "root_cause": "Model underestimated downside"
    },
    {
      "prediction_date": "2025-08-11",
      "predicted_90d": 5.5,
      "actual_90d": -18.2,
      "error": 23.7,
      "direction_correct": "False",
      "composite_score": 65.7,
      "sector": "Real Estate",
      "rate_regime": "stable",
      "root_cause": "Model underestimated downside"
    }
  ]
}