{
  "sym": "7030",
  "name": "Zain Saudi",
  "generated": "2026-06-06T01:57:26.609589",
  "signals": [
    {
      "signal": "RSI Extreme Oversold (0-20)",
      "group": "Technical \u2014 RSI",
      "occurrences": 51,
      "avg_return_30d": -2.86,
      "pct_positive_30d": 35.3,
      "p_value_30d": 0.152,
      "significant_30d": false,
      "avg_alpha_30d": 4.67,
      "avg_return_60d": 0.74,
      "pct_positive_60d": 47.1,
      "p_value_60d": 0.824,
      "significant_60d": false,
      "avg_alpha_60d": 4.67,
      "avg_return_90d": 4.63,
      "pct_positive_90d": 51.0,
      "p_value_90d": 0.195,
      "significant_90d": false,
      "avg_alpha_90d": 4.67,
      "reliability_score": 45,
      "reliability_label": "MEDIUM"
    },
    {
      "signal": "RSI Oversold (20-30)",
      "group": "Technical \u2014 RSI",
      "occurrences": 135,
      "avg_return_30d": -0.76,
      "pct_positive_30d": 40.7,
      "p_value_30d": 0.517,
      "significant_30d": false,
      "avg_alpha_30d": 0.69,
      "avg_return_60d": 0.3,
      "pct_positive_60d": 37.8,
      "p_value_60d": 0.863,
      "significant_60d": false,
      "avg_alpha_60d": 0.69,
      "avg_return_90d": 3.11,
      "pct_positive_90d": 48.9,
      "p_value_90d": 0.134,
      "significant_90d": false,
      "avg_alpha_90d": 0.69,
      "reliability_score": 45,
      "reliability_label": "MEDIUM"
    },
    {
      "signal": "RSI Low (30-40)",
      "group": "Technical \u2014 RSI",
      "occurrences": 219,
      "avg_return_30d": 1.03,
      "pct_positive_30d": 46.1,
      "p_value_30d": 0.317,
      "significant_30d": false,
      "avg_alpha_30d": 1.25,
      "avg_return_60d": 2.52,
      "pct_positive_60d": 44.7,
      "p_value_60d": 0.059,
      "significant_60d": false,
      "avg_alpha_60d": 1.25,
      "avg_return_90d": 3.93,
      "pct_positive_90d": 50.7,
      "p_value_90d": 0.015,
      "significant_90d": true,
      "avg_alpha_90d": 1.25,
      "reliability_score": 75,
      "reliability_label": "HIGH"
    },
    {
      "signal": "RSI Neutral-Low (40-50)",
      "group": "Technical \u2014 RSI",
      "occurrences": 256,
      "avg_return_30d": 2.94,
      "pct_positive_30d": 49.2,
      "p_value_30d": 0.005,
      "significant_30d": true,
      "avg_alpha_30d": 0.34,
      "avg_return_60d": 2.98,
      "pct_positive_60d": 46.9,
      "p_value_60d": 0.033,
      "significant_60d": true,
      "avg_alpha_60d": 0.34,
      "avg_return_90d": 2.3,
      "pct_positive_90d": 50.4,
      "p_value_90d": 0.103,
      "significant_90d": false,
      "avg_alpha_90d": 0.34,
      "reliability_score": 45,
      "reliability_label": "MEDIUM"
    },
    {
      "signal": "RSI Neutral-High (50-60)",
      "group": "Technical \u2014 RSI",
      "occurrences": 256,
      "avg_return_30d": 1.2,
      "pct_positive_30d": 44.9,
      "p_value_30d": 0.211,
      "significant_30d": false,
      "avg_alpha_30d": 0.64,
      "avg_return_60d": 2.2,
      "pct_positive_60d": 46.1,
      "p_value_60d": 0.083,
      "significant_60d": false,
      "avg_alpha_60d": 0.64,
      "avg_return_90d": 2.24,
      "pct_positive_90d": 47.3,
      "p_value_90d": 0.119,
      "significant_90d": false,
      "avg_alpha_90d": 0.64,
      "reliability_score": 45,
      "reliability_label": "MEDIUM"
    },
    {
      "signal": "RSI High (60-70)",
      "group": "Technical \u2014 RSI",
      "occurrences": 200,
      "avg_return_30d": 1.35,
      "pct_positive_30d": 41.5,
      "p_value_30d": 0.198,
      "significant_30d": false,
      "avg_alpha_30d": 0.45,
      "avg_return_60d": 2.51,
      "pct_positive_60d": 47.0,
      "p_value_60d": 0.1,
      "significant_60d": false,
      "avg_alpha_60d": 0.45,
      "avg_return_90d": 2.1,
      "pct_positive_90d": 51.0,
      "p_value_90d": 0.22,
      "significant_90d": false,
      "avg_alpha_90d": 0.45,
      "reliability_score": 45,
      "reliability_label": "MEDIUM"
    },
    {
      "signal": "RSI Overbought (70-80)",
      "group": "Technical \u2014 RSI",
      "occurrences": 109,
      "avg_return_30d": 1.06,
      "pct_positive_30d": 45.9,
      "p_value_30d": 0.524,
      "significant_30d": false,
      "avg_alpha_30d": -0.37,
      "avg_return_60d": -1.13,
      "pct_positive_60d": 45.0,
      "p_value_60d": 0.552,
      "significant_60d": false,
      "avg_alpha_60d": -0.37,
      "avg_return_90d": 0.95,
      "pct_positive_90d": 45.9,
      "p_value_90d": 0.722,
      "significant_90d": false,
      "avg_alpha_90d": -0.37,
      "reliability_score": 35,
      "reliability_label": "MEDIUM"
    },
    {
      "signal": "RSI Extreme Overbought (80-100)",
      "group": "Technical \u2014 RSI",
      "occurrences": 46,
      "avg_return_30d": 1.13,
      "pct_positive_30d": 41.3,
      "p_value_30d": 0.705,
      "significant_30d": false,
      "avg_alpha_30d": -3.18,
      "avg_return_60d": 0.93,
      "pct_positive_60d": 50.0,
      "p_value_60d": 0.765,
      "significant_60d": false,
      "avg_alpha_60d": -3.18,
      "avg_return_90d": -2.56,
      "pct_positive_90d": 47.8,
      "p_value_90d": 0.481,
      "significant_90d": false,
      "avg_alpha_90d": -3.18,
      "reliability_score": 45,
      "reliability_label": "MEDIUM"
    },
    {
      "signal": "BB Near Lower Band",
      "group": "Technical \u2014 BB",
      "occurrences": 89,
      "avg_return_30d": 0.38,
      "pct_positive_30d": 43.8,
      "p_value_30d": 0.841,
      "significant_30d": false,
      "avg_alpha_30d": 2.27,
      "avg_return_60d": 3.21,
      "pct_positive_60d": 39.3,
      "p_value_60d": 0.226,
      "significant_60d": false,
      "avg_alpha_60d": 2.27,
      "avg_return_90d": 4.28,
      "pct_positive_90d": 47.2,
      "p_value_90d": 0.134,
      "significant_90d": false,
      "avg_alpha_90d": 2.27,
      "reliability_score": 45,
      "reliability_label": "MEDIUM"
    },
    {
      "signal": "BB Near Upper Band",
      "group": "Technical \u2014 BB",
      "occurrences": 92,
      "avg_return_30d": 1.78,
      "pct_positive_30d": 45.7,
      "p_value_30d": 0.285,
      "significant_30d": false,
      "avg_alpha_30d": 0.44,
      "avg_return_60d": 1.68,
      "pct_positive_60d": 50.0,
      "p_value_60d": 0.453,
      "significant_60d": false,
      "avg_alpha_60d": 0.44,
      "avg_return_90d": 1.78,
      "pct_positive_90d": 51.1,
      "p_value_90d": 0.469,
      "significant_90d": false,
      "avg_alpha_90d": 0.44,
      "reliability_score": 35,
      "reliability_label": "MEDIUM"
    },
    {
      "signal": "Strong Momentum >10%",
      "group": "Technical \u2014 Momentum",
      "occurrences": 45,
      "avg_return_30d": 3.07,
      "pct_positive_30d": 51.1,
      "p_value_30d": 0.334,
      "significant_30d": false,
      "avg_alpha_30d": -0.78,
      "avg_return_60d": 4.01,
      "pct_positive_60d": 53.3,
      "p_value_60d": 0.236,
      "significant_60d": false,
      "avg_alpha_60d": -0.78,
      "avg_return_90d": 2.2,
      "pct_positive_90d": 44.4,
      "p_value_90d": 0.583,
      "significant_90d": false,
      "avg_alpha_90d": -0.78,
      "reliability_score": 45,
      "reliability_label": "MEDIUM"
    },
    {
      "signal": "Weak Momentum <-10%",
      "group": "Technical \u2014 Momentum",
      "occurrences": 38,
      "avg_return_30d": 1.2,
      "pct_positive_30d": 50.0,
      "p_value_30d": 0.752,
      "significant_30d": false,
      "avg_alpha_30d": 5.79,
      "avg_return_60d": 1.97,
      "pct_positive_60d": 47.4,
      "p_value_60d": 0.584,
      "significant_60d": false,
      "avg_alpha_60d": 5.79,
      "avg_return_90d": 7.14,
      "pct_positive_90d": 55.3,
      "p_value_90d": 0.092,
      "significant_90d": false,
      "avg_alpha_90d": 5.79,
      "reliability_score": 55,
      "reliability_label": "MEDIUM"
    },
    {
      "signal": "Below All MAs",
      "group": "Technical \u2014 MA",
      "occurrences": 62,
      "avg_return_30d": 1.4,
      "pct_positive_30d": 50.0,
      "p_value_30d": 0.496,
      "significant_30d": false,
      "avg_alpha_30d": -0.72,
      "avg_return_60d": 0.64,
      "pct_positive_60d": 43.5,
      "p_value_60d": 0.79,
      "significant_60d": false,
      "avg_alpha_60d": -0.72,
      "avg_return_90d": 0.77,
      "pct_positive_90d": 40.3,
      "p_value_90d": 0.773,
      "significant_90d": false,
      "avg_alpha_90d": -0.72,
      "reliability_score": 35,
      "reliability_label": "MEDIUM"
    },
    {
      "signal": "Above All MAs",
      "group": "Technical \u2014 MA",
      "occurrences": 68,
      "avg_return_30d": 0.71,
      "pct_positive_30d": 45.6,
      "p_value_30d": 0.701,
      "significant_30d": false,
      "avg_alpha_30d": -6.62,
      "avg_return_60d": -2.07,
      "pct_positive_60d": 39.7,
      "p_value_60d": 0.308,
      "significant_60d": false,
      "avg_alpha_60d": -6.62,
      "avg_return_90d": -5.45,
      "pct_positive_90d": 47.1,
      "p_value_90d": 0.015,
      "significant_90d": true,
      "avg_alpha_90d": -6.62,
      "reliability_score": 85,
      "reliability_label": "HIGH"
    },
    {
      "signal": "Rate Regime: rising",
      "group": "Macro \u2014 Rates",
      "occurrences": 5,
      "avg_return_30d": 0.51,
      "pct_positive_30d": 40.0,
      "p_value_30d": 0.945,
      "significant_30d": false,
      "avg_alpha_30d": 3.46,
      "avg_return_60d": 1.15,
      "pct_positive_60d": 40.0,
      "p_value_60d": 0.897,
      "significant_60d": false,
      "avg_alpha_60d": 3.46,
      "avg_return_90d": 2.49,
      "pct_positive_90d": 40.0,
      "p_value_90d": 0.821,
      "significant_90d": false,
      "avg_alpha_90d": 3.46,
      "reliability_score": 10,
      "reliability_label": "LOW"
    },
    {
      "signal": "Rate Regime: stable",
      "group": "Macro \u2014 Rates",
      "occurrences": 9,
      "avg_return_30d": 1.83,
      "pct_positive_30d": 33.3,
      "p_value_30d": 0.767,
      "significant_30d": false,
      "avg_alpha_30d": 8.79,
      "avg_return_60d": 5.1,
      "pct_positive_60d": 55.6,
      "p_value_60d": 0.522,
      "significant_60d": false,
      "avg_alpha_60d": 8.79,
      "avg_return_90d": 6.6,
      "pct_positive_90d": 66.7,
      "p_value_90d": 0.39,
      "significant_90d": false,
      "avg_alpha_90d": 8.79,
      "reliability_score": 20,
      "reliability_label": "LOW"
    },
    {
      "signal": "Rate Regime: falling",
      "group": "Macro \u2014 Rates",
      "occurrences": 3,
      "reliability_label": "INSUFFICIENT"
    },
    {
      "signal": "VIX > 30 (fear)",
      "group": "Macro \u2014 Risk",
      "occurrences": 21,
      "avg_return_30d": 0.96,
      "pct_positive_30d": 52.4,
      "p_value_30d": 0.621,
      "significant_30d": false,
      "avg_alpha_30d": -5.2,
      "avg_return_60d": 1.43,
      "pct_positive_60d": 57.1,
      "p_value_60d": 0.553,
      "significant_60d": false,
      "avg_alpha_60d": -5.2,
      "avg_return_90d": -1.21,
      "pct_positive_90d": 47.6,
      "p_value_90d": 0.729,
      "significant_90d": false,
      "avg_alpha_90d": -5.2,
      "reliability_score": 20,
      "reliability_label": "LOW"
    },
    {
      "signal": "VIX < 15 (calm)",
      "group": "Macro \u2014 Risk",
      "occurrences": 42,
      "avg_return_30d": -0.94,
      "pct_positive_30d": 50.0,
      "p_value_30d": 0.685,
      "significant_30d": false,
      "avg_alpha_30d": 3.12,
      "avg_return_60d": 0.22,
      "pct_positive_60d": 40.5,
      "p_value_60d": 0.946,
      "significant_60d": false,
      "avg_alpha_60d": 3.12,
      "avg_return_90d": 2.05,
      "pct_positive_90d": 47.6,
      "p_value_90d": 0.577,
      "significant_90d": false,
      "avg_alpha_90d": 3.12,
      "reliability_score": 45,
      "reliability_label": "MEDIUM"
    },
    {
      "signal": "Oil Uptrend",
      "group": "Macro \u2014 Oil",
      "occurrences": 30,
      "avg_return_30d": 1.77,
      "pct_positive_30d": 46.7,
      "p_value_30d": 0.628,
      "significant_30d": false,
      "avg_alpha_30d": 3.64,
      "avg_return_60d": 0.23,
      "pct_positive_60d": 53.3,
      "p_value_60d": 0.955,
      "significant_60d": false,
      "avg_alpha_60d": 3.64,
      "avg_return_90d": 5.63,
      "pct_positive_90d": 60.0,
      "p_value_90d": 0.269,
      "significant_90d": false,
      "avg_alpha_90d": 3.64,
      "reliability_score": 40,
      "reliability_label": "MEDIUM"
    },
    {
      "signal": "Oil Downtrend",
      "group": "Macro \u2014 Oil",
      "occurrences": 26,
      "avg_return_30d": 0.16,
      "pct_positive_30d": 46.2,
      "p_value_30d": 0.958,
      "significant_30d": false,
      "avg_alpha_30d": 0.31,
      "avg_return_60d": 0.05,
      "pct_positive_60d": 38.5,
      "p_value_60d": 0.989,
      "significant_60d": false,
      "avg_alpha_60d": 0.31,
      "avg_return_90d": 0.46,
      "pct_positive_90d": 42.3,
      "p_value_90d": 0.912,
      "significant_90d": false,
      "avg_alpha_90d": 0.31,
      "reliability_score": 20,
      "reliability_label": "LOW"
    },
    {
      "signal": "TASI Uptrend >5%",
      "group": "Macro \u2014 TASI",
      "occurrences": 67,
      "avg_return_30d": 3.01,
      "pct_positive_30d": 52.2,
      "p_value_30d": 0.155,
      "significant_30d": false,
      "avg_alpha_30d": 0.17,
      "avg_return_60d": 2.62,
      "pct_positive_60d": 43.3,
      "p_value_60d": 0.34,
      "significant_60d": false,
      "avg_alpha_60d": 0.17,
      "avg_return_90d": 1.56,
      "pct_positive_90d": 41.8,
      "p_value_90d": 0.657,
      "significant_90d": false,
      "avg_alpha_90d": 0.17,
      "reliability_score": 35,
      "reliability_label": "MEDIUM"
    },
    {
      "signal": "TASI Downtrend >5%",
      "group": "Macro \u2014 TASI",
      "occurrences": 39,
      "avg_return_30d": 0.61,
      "pct_positive_30d": 51.3,
      "p_value_30d": 0.805,
      "significant_30d": false,
      "avg_alpha_30d": 1.07,
      "avg_return_60d": 1.56,
      "pct_positive_60d": 53.8,
      "p_value_60d": 0.585,
      "significant_60d": false,
      "avg_alpha_60d": 1.07,
      "avg_return_90d": 2.71,
      "pct_positive_90d": 53.8,
      "p_value_90d": 0.38,
      "significant_90d": false,
      "avg_alpha_90d": 1.07,
      "reliability_score": 30,
      "reliability_label": "LOW"
    },
    {
      "signal": "Outperform TASI >5%",
      "group": "Relative Strength",
      "occurrences": 61,
      "avg_return_30d": 1.29,
      "pct_positive_30d": 42.6,
      "p_value_30d": 0.616,
      "significant_30d": false,
      "avg_alpha_30d": 0.01,
      "avg_return_60d": 2.17,
      "pct_positive_60d": 45.9,
      "p_value_60d": 0.444,
      "significant_60d": false,
      "avg_alpha_60d": 0.01,
      "avg_return_90d": 1.77,
      "pct_positive_90d": 49.2,
      "p_value_90d": 0.566,
      "significant_90d": false,
      "avg_alpha_90d": 0.01,
      "reliability_score": 35,
      "reliability_label": "MEDIUM"
    },
    {
      "signal": "Underperform TASI >5%",
      "group": "Relative Strength",
      "occurrences": 89,
      "avg_return_30d": 0.97,
      "pct_positive_30d": 46.1,
      "p_value_30d": 0.604,
      "significant_30d": false,
      "avg_alpha_30d": 1.04,
      "avg_return_60d": -0.11,
      "pct_positive_60d": 42.7,
      "p_value_60d": 0.957,
      "significant_60d": false,
      "avg_alpha_60d": 1.04,
      "avg_return_90d": 2.12,
      "pct_positive_90d": 48.3,
      "p_value_90d": 0.394,
      "significant_90d": false,
      "avg_alpha_90d": 1.04,
      "reliability_score": 45,
      "reliability_label": "MEDIUM"
    },
    {
      "signal": "RSI Oversold + Stable Rates",
      "group": "Mean Reversion",
      "occurrences": 88,
      "avg_return_30d": -0.06,
      "pct_positive_30d": 42.0,
      "p_value_30d": 0.972,
      "significant_30d": false,
      "avg_alpha_30d": -2.5,
      "avg_return_60d": 0.34,
      "pct_positive_60d": 42.0,
      "p_value_60d": 0.886,
      "significant_60d": false,
      "avg_alpha_60d": -2.5,
      "avg_return_90d": -0.12,
      "pct_positive_90d": 44.3,
      "p_value_90d": 0.961,
      "significant_90d": false,
      "avg_alpha_90d": -2.5,
      "reliability_score": 35,
      "reliability_label": "MEDIUM"
    },
    {
      "signal": "RSI Oversold + Low VIX",
      "group": "Mean Reversion",
      "occurrences": 86,
      "avg_return_30d": -0.32,
      "pct_positive_30d": 40.7,
      "p_value_30d": 0.848,
      "significant_30d": false,
      "avg_alpha_30d": -1.8,
      "avg_return_60d": -0.96,
      "pct_positive_60d": 38.4,
      "p_value_60d": 0.663,
      "significant_60d": false,
      "avg_alpha_60d": -1.8,
      "avg_return_90d": -1.72,
      "pct_positive_90d": 40.7,
      "p_value_90d": 0.435,
      "significant_90d": false,
      "avg_alpha_90d": -1.8,
      "reliability_score": 35,
      "reliability_label": "MEDIUM"
    },
    {
      "signal": "BB Lower + Stable Rates",
      "group": "Mean Reversion",
      "occurrences": 78,
      "avg_return_30d": 0.05,
      "pct_positive_30d": 42.3,
      "p_value_30d": 0.981,
      "significant_30d": false,
      "avg_alpha_30d": 1.55,
      "avg_return_60d": 3.21,
      "pct_positive_60d": 42.3,
      "p_value_60d": 0.267,
      "significant_60d": false,
      "avg_alpha_60d": 1.55,
      "avg_return_90d": 4.05,
      "pct_positive_90d": 48.7,
      "p_value_90d": 0.195,
      "significant_90d": false,
      "avg_alpha_90d": 1.55,
      "reliability_score": 45,
      "reliability_label": "MEDIUM"
    },
    {
      "signal": "Volume Surge >2.5x",
      "group": "Technical \u2014 Volume",
      "occurrences": 155,
      "avg_return_30d": 1.03,
      "pct_positive_30d": 41.9,
      "p_value_30d": 0.358,
      "significant_30d": false,
      "avg_alpha_30d": 0.48,
      "avg_return_60d": 1.9,
      "pct_positive_60d": 45.8,
      "p_value_60d": 0.282,
      "significant_60d": false,
      "avg_alpha_60d": 0.48,
      "avg_return_90d": 2.54,
      "pct_positive_90d": 49.0,
      "p_value_90d": 0.222,
      "significant_90d": false,
      "avg_alpha_90d": 0.48,
      "reliability_score": 45,
      "reliability_label": "MEDIUM"
    },
    {
      "signal": "Price >20% Below 52w High",
      "group": "Technical \u2014 Momentum",
      "occurrences": 27,
      "avg_return_30d": -0.43,
      "pct_positive_30d": 55.6,
      "p_value_30d": 0.815,
      "significant_30d": false,
      "avg_alpha_30d": 1.73,
      "avg_return_60d": 1.87,
      "pct_positive_60d": 44.4,
      "p_value_60d": 0.657,
      "significant_60d": false,
      "avg_alpha_60d": 1.73,
      "avg_return_90d": 1.06,
      "pct_positive_90d": 48.1,
      "p_value_90d": 0.786,
      "significant_90d": false,
      "avg_alpha_90d": 1.73,
      "reliability_score": 20,
      "reliability_label": "LOW"
    },
    {
      "signal": "Annual NI growth >20% YoY",
      "group": "Fundamental \u2014 Financial",
      "occurrences": 5,
      "avg_return_90d": 5.83,
      "pct_positive_90d": 40.0,
      "p_value_90d": 0.683,
      "significant_90d": false,
      "edge_vs_base": 3.24,
      "reliability_label": "LOW"
    },
    {
      "signal": "Annual NI decline YoY",
      "group": "Fundamental \u2014 Financial",
      "occurrences": 10,
      "avg_return_90d": 16.34,
      "pct_positive_90d": 80.0,
      "p_value_90d": 0.146,
      "significant_90d": false,
      "edge_vs_base": 13.74,
      "reliability_label": "LOW"
    },
    {
      "signal": "High cash flow quality (OCF/NI >1.2)",
      "group": "Fundamental \u2014 Financial",
      "occurrences": 9,
      "avg_return_90d": 5.78,
      "pct_positive_90d": 66.7,
      "p_value_90d": 0.487,
      "significant_90d": false,
      "edge_vs_base": 3.18,
      "reliability_label": "LOW"
    },
    {
      "signal": "Low cash flow quality (OCF/NI <0.3)",
      "group": "Fundamental \u2014 Financial",
      "occurrences": 7,
      "avg_return_90d": 22.25,
      "pct_positive_90d": 71.4,
      "p_value_90d": 0.157,
      "significant_90d": false,
      "edge_vs_base": 19.66,
      "reliability_label": "LOW"
    }
  ],
  "baseline": {
    "n": 3904,
    "avg_30d": 1.0,
    "avg_90d": 2.6,
    "win_pct": 48.8
  }
}