{
  "sym": "7200",
  "name": "Al Moammar Info Systems",
  "generated": "2026-06-06T01:57:29.472770",
  "validation": {
    "n_predictions": 25,
    "directional_accuracy_pct": 56.0,
    "baseline_always_long_pct": 68.0,
    "edge_over_baseline_pct": -12.0,
    "mae_pct": 22.59,
    "avg_predicted_90d": 2.24,
    "avg_actual_90d": 14.42,
    "systematic_bias": 12.18,
    "fund_weight_used": 0.3,
    "regime_breakdown": {
      "rising": {
        "n": 4,
        "accuracy": 25.0
      },
      "stable": {
        "n": 18,
        "accuracy": 61.1
      },
      "falling": {
        "n": 3,
        "accuracy": 66.7
      }
    }
  },
  "predictions": [
    {
      "prediction_date": "2020-01-30",
      "price": 21.86,
      "rate_regime": "stable",
      "rsi": 51.2,
      "vix": 15.5,
      "env_score": 70,
      "tech_score": 50,
      "fund_score": 67,
      "composite": 63.1,
      "base_30d_pct": 2.0,
      "base_60d_pct": 3.5,
      "base_90d_pct": 5.0,
      "confidence": 69,
      "actual_30d_pct": -10.8,
      "hit_target_30d": "False",
      "actual_60d_pct": 12.5,
      "hit_target_60d": "True",
      "actual_90d_pct": 17.9,
      "hit_target_90d": "True"
    },
    {
      "prediction_date": "2020-04-29",
      "price": 25.35,
      "rate_regime": "falling",
      "rsi": 64.7,
      "vix": 31.2,
      "env_score": 60,
      "tech_score": 40,
      "fund_score": 67,
      "composite": 56.1,
      "base_30d_pct": 0.8,
      "base_60d_pct": 1.4,
      "base_90d_pct": 2.0,
      "confidence": 64,
      "actual_30d_pct": 2.1,
      "hit_target_30d": "True",
      "actual_60d_pct": 33.7,
      "hit_target_60d": "True",
      "actual_90d_pct": 50.0,
      "hit_target_90d": "True"
    },
    {
      "prediction_date": "2020-07-28",
      "price": 33.22,
      "rate_regime": "stable",
      "rsi": 76.6,
      "vix": 25.4,
      "env_score": 85,
      "tech_score": 18,
      "fund_score": 67,
      "composite": 59.5,
      "base_30d_pct": 2.0,
      "base_60d_pct": 3.5,
      "base_90d_pct": 5.0,
      "confidence": 54,
      "actual_30d_pct": 15.5,
      "hit_target_30d": "True",
      "actual_60d_pct": 33.6,
      "hit_target_60d": "True",
      "actual_90d_pct": 55.4,
      "hit_target_90d": "True"
    },
    {
      "prediction_date": "2020-10-26",
      "price": 44.2,
      "rate_regime": "stable",
      "rsi": 62.2,
      "vix": 32.5,
      "env_score": 85,
      "tech_score": 40,
      "fund_score": 67,
      "composite": 66.1,
      "base_30d_pct": 2.8,
      "base_60d_pct": 4.9,
      "base_90d_pct": 7.0,
      "confidence": 65,
      "actual_30d_pct": 14.7,
      "hit_target_30d": "True",
      "actual_60d_pct": 32.4,
      "hit_target_60d": "True",
      "actual_90d_pct": 75.7,
      "hit_target_90d": "True"
    },
    {
      "prediction_date": "2021-01-24",
      "price": 60.42,
      "rate_regime": "stable",
      "rsi": 52.0,
      "vix": 21.3,
      "env_score": 85,
      "tech_score": 30,
      "fund_score": 52,
      "composite": 58.6,
      "base_30d_pct": 2.0,
      "base_60d_pct": 3.5,
      "base_90d_pct": 5.0,
      "confidence": 57,
      "actual_30d_pct": 38.4,
      "hit_target_30d": "True",
      "actual_60d_pct": 45.1,
      "hit_target_60d": "True",
      "actual_90d_pct": 38.1,
      "hit_target_90d": "True"
    },
    {
      "prediction_date": "2021-04-25",
      "price": 86.14,
      "rate_regime": "stable",
      "rsi": 41.8,
      "vix": 18.7,
      "env_score": 80,
      "tech_score": 50,
      "fund_score": 52,
      "composite": 62.6,
      "base_30d_pct": 2.0,
      "base_60d_pct": 3.5,
      "base_90d_pct": 5.0,
      "confidence": 66,
      "actual_30d_pct": 1.4,
      "hit_target_30d": "True",
      "actual_60d_pct": 35.2,
      "hit_target_60d": "True",
      "actual_90d_pct": 54.3,
      "hit_target_90d": "True"
    },
    {
      "prediction_date": "2021-07-25",
      "price": 119.04,
      "rate_regime": "stable",
      "rsi": 73.1,
      "vix": 17.0,
      "env_score": 80,
      "tech_score": 18,
      "fund_score": 52,
      "composite": 53.0,
      "base_30d_pct": 1.2,
      "base_60d_pct": 2.1,
      "base_90d_pct": 3.0,
      "confidence": 51,
      "actual_30d_pct": 9.6,
      "hit_target_30d": "True",
      "actual_60d_pct": 0.0,
      "hit_target_60d": "False",
      "actual_90d_pct": -5.6,
      "hit_target_90d": "False"
    },
    {
      "prediction_date": "2021-10-21",
      "price": 121.05,
      "rate_regime": "stable",
      "rsi": 38.0,
      "vix": 15.0,
      "env_score": 80,
      "tech_score": 58,
      "fund_score": 52,
      "composite": 65.0,
      "base_30d_pct": 2.0,
      "base_60d_pct": 3.5,
      "base_90d_pct": 5.0,
      "confidence": 70,
      "actual_30d_pct": -7.1,
      "hit_target_30d": "False",
      "actual_60d_pct": 2.3,
      "hit_target_60d": "True",
      "actual_90d_pct": -4.2,
      "hit_target_90d": "False"
    },
    {
      "prediction_date": "2022-01-19",
      "price": 122.57,
      "rate_regime": "stable",
      "rsi": 63.7,
      "vix": 23.9,
      "env_score": 75,
      "tech_score": 40,
      "fund_score": 45,
      "composite": 55.5,
      "base_30d_pct": 1.2,
      "base_60d_pct": 2.1,
      "base_90d_pct": 3.0,
      "confidence": 60,
      "actual_30d_pct": -8.4,
      "hit_target_30d": "False",
      "actual_60d_pct": -12.6,
      "hit_target_60d": "False",
      "actual_90d_pct": -25.3,
      "hit_target_90d": "False"
    },
    {
      "prediction_date": "2022-04-19",
      "price": 105.87,
      "rate_regime": "stable",
      "rsi": 31.8,
      "vix": 21.4,
      "env_score": 85,
      "tech_score": 58,
      "fund_score": 45,
      "composite": 64.9,
      "base_30d_pct": 2.0,
      "base_60d_pct": 3.5,
      "base_90d_pct": 5.0,
      "confidence": 68,
      "actual_30d_pct": -14.9,
      "hit_target_30d": "False",
      "actual_60d_pct": -20.7,
      "hit_target_60d": "False",
      "actual_90d_pct": -15.9,
      "hit_target_90d": "False"
    },
    {
      "prediction_date": "2022-07-18",
      "price": 78.82,
      "rate_regime": "rising",
      "rsi": 40.3,
      "vix": 25.3,
      "env_score": 30,
      "tech_score": 50,
      "fund_score": 45,
      "composite": 40.5,
      "base_30d_pct": -3.2,
      "base_60d_pct": -5.6,
      "base_90d_pct": -8.0,
      "confidence": 66,
      "actual_30d_pct": 21.9,
      "hit_target_30d": "False",
      "actual_60d_pct": 20.1,
      "hit_target_60d": "False",
      "actual_90d_pct": 7.3,
      "hit_target_90d": "False"
    },
    {
      "prediction_date": "2022-10-16",
      "price": 95.97,
      "rate_regime": "rising",
      "rsi": 77.8,
      "vix": 31.9,
      "env_score": 40,
      "tech_score": 38,
      "fund_score": 45,
      "composite": 40.9,
      "base_30d_pct": -3.2,
      "base_60d_pct": -5.6,
      "base_90d_pct": -8.0,
      "confidence": 70,
      "actual_30d_pct": -7.6,
      "hit_target_30d": "True",
      "actual_60d_pct": -8.5,
      "hit_target_60d": "True",
      "actual_90d_pct": -3.2,
      "hit_target_90d": "True"
    },
    {
      "prediction_date": "2023-01-15",
      "price": 88.96,
      "rate_regime": "rising",
      "rsi": 70.2,
      "vix": 18.8,
      "env_score": 25,
      "tech_score": 38,
      "fund_score": 83,
      "composite": 46.3,
      "base_30d_pct": -1.6,
      "base_60d_pct": -2.8,
      "base_90d_pct": -4.0,
      "confidence": 64,
      "actual_30d_pct": 2.0,
      "hit_target_30d": "False",
      "actual_60d_pct": 21.1,
      "hit_target_60d": "False",
      "actual_90d_pct": 38.4,
      "hit_target_90d": "False"
    },
    {
      "prediction_date": "2023-04-16",
      "price": 113.44,
      "rate_regime": "rising",
      "rsi": 71.6,
      "vix": 17.8,
      "env_score": 25,
      "tech_score": 28,
      "fund_score": 83,
      "composite": 43.3,
      "base_30d_pct": -1.6,
      "base_60d_pct": -2.8,
      "base_90d_pct": -4.0,
      "confidence": 68,
      "actual_30d_pct": 15.7,
      "hit_target_30d": "False",
      "actual_60d_pct": 42.5,
      "hit_target_60d": "False",
      "actual_90d_pct": 36.2,
      "hit_target_90d": "False"
    },
    {
      "prediction_date": "2023-07-13",
      "price": 157.12,
      "rate_regime": "stable",
      "rsi": 71.2,
      "vix": 13.6,
      "env_score": 65,
      "tech_score": 3,
      "fund_score": 83,
      "composite": 51.8,
      "base_30d_pct": 1.2,
      "base_60d_pct": 2.1,
      "base_90d_pct": 3.0,
      "confidence": 50,
      "actual_30d_pct": 1.9,
      "hit_target_30d": "True",
      "actual_60d_pct": -18.7,
      "hit_target_60d": "False",
      "actual_90d_pct": -24.1,
      "hit_target_90d": "False"
    },
    {
      "prediction_date": "2023-10-11",
      "price": 125.52,
      "rate_regime": "stable",
      "rsi": 35.8,
      "vix": 16.1,
      "env_score": 70,
      "tech_score": 78,
      "fund_score": 83,
      "composite": 76.3,
      "base_30d_pct": 3.6,
      "base_60d_pct": 6.3,
      "base_90d_pct": 9.0,
      "confidence": 81,
      "actual_30d_pct": -5.6,
      "hit_target_30d": "False",
      "actual_60d_pct": 3.0,
      "hit_target_60d": "True",
      "actual_90d_pct": 12.5,
      "hit_target_90d": "True"
    },
    {
      "prediction_date": "2024-01-09",
      "price": 130.48,
      "rate_regime": "stable",
      "rsi": 58.9,
      "vix": 12.8,
      "env_score": 65,
      "tech_score": 50,
      "fund_score": 26,
      "composite": 48.8,
      "base_30d_pct": 0.4,
      "base_60d_pct": 0.7,
      "base_90d_pct": 1.0,
      "confidence": 62,
      "actual_30d_pct": 8.6,
      "hit_target_30d": "True",
      "actual_60d_pct": 9.6,
      "hit_target_60d": "True",
      "actual_90d_pct": 5.0,
      "hit_target_90d": "True"
    },
    {
      "prediction_date": "2024-04-15",
      "price": 150.89,
      "rate_regime": "stable",
      "rsi": 66.7,
      "vix": 19.2,
      "env_score": 80,
      "tech_score": 35,
      "fund_score": 26,
      "composite": 50.3,
      "base_30d_pct": 1.2,
      "base_60d_pct": 2.1,
      "base_90d_pct": 3.0,
      "confidence": 53,
      "actual_30d_pct": -6.4,
      "hit_target_30d": "False",
      "actual_60d_pct": 7.7,
      "hit_target_60d": "True",
      "actual_90d_pct": 7.3,
      "hit_target_90d": "True"
    },
    {
      "prediction_date": "2024-07-07",
      "price": 160.23,
      "rate_regime": "stable",
      "rsi": 74.3,
      "vix": 12.1,
      "env_score": 65,
      "tech_score": 18,
      "fund_score": 26,
      "composite": 39.2,
      "base_30d_pct": -1.2,
      "base_60d_pct": -2.1,
      "base_90d_pct": -3.0,
      "confidence": 60,
      "actual_30d_pct": 3.6,
      "hit_target_30d": "False",
      "actual_60d_pct": 16.3,
      "hit_target_60d": "False",
      "actual_90d_pct": 15.6,
      "hit_target_90d": "False"
    },
    {
      "prediction_date": "2024-10-06",
      "price": 169.96,
      "rate_regime": "stable",
      "rsi": 36.1,
      "vix": 20.5,
      "env_score": 75,
      "tech_score": 78,
      "fund_score": 26,
      "composite": 61.2,
      "base_30d_pct": 2.0,
      "base_60d_pct": 3.5,
      "base_90d_pct": 5.0,
      "confidence": 72,
      "actual_30d_pct": 4.6,
      "hit_target_30d": "True",
      "actual_60d_pct": -9.0,
      "hit_target_60d": "False",
      "actual_90d_pct": -14.0,
      "hit_target_90d": "False"
    },
    {
      "prediction_date": "2025-01-05",
      "price": 154.7,
      "rate_regime": "falling",
      "rsi": 39.0,
      "vix": 17.9,
      "env_score": 45,
      "tech_score": 58,
      "fund_score": 58,
      "composite": 52.8,
      "base_30d_pct": 0.8,
      "base_60d_pct": 1.4,
      "base_90d_pct": 2.0,
      "confidence": 63,
      "actual_30d_pct": -10.9,
      "hit_target_30d": "False",
      "actual_60d_pct": -23.4,
      "hit_target_60d": "False",
      "actual_90d_pct": -14.0,
      "hit_target_90d": "False"
    },
    {
      "prediction_date": "2025-04-03",
      "price": 125.9,
      "rate_regime": "falling",
      "rsi": 46.8,
      "vix": 30.0,
      "env_score": 60,
      "tech_score": 50,
      "fund_score": 58,
      "composite": 56.4,
      "base_30d_pct": 0.8,
      "base_60d_pct": 1.4,
      "base_90d_pct": 2.0,
      "confidence": 66,
      "actual_30d_pct": 5.7,
      "hit_target_30d": "True",
      "actual_60d_pct": 4.9,
      "hit_target_60d": "True",
      "actual_90d_pct": 1.0,
      "hit_target_90d": "True"
    },
    {
      "prediction_date": "2025-07-02",
      "price": 132.04,
      "rate_regime": "stable",
      "rsi": 42.2,
      "vix": 16.6,
      "env_score": 70,
      "tech_score": 50,
      "fund_score": 58,
      "composite": 60.4,
      "base_30d_pct": 2.0,
      "base_60d_pct": 3.5,
      "base_90d_pct": 5.0,
      "confidence": 67,
      "actual_30d_pct": -3.7,
      "hit_target_30d": "False",
      "actual_60d_pct": 2.8,
      "hit_target_60d": "True",
      "actual_90d_pct": 8.7,
      "hit_target_90d": "True"
    },
    {
      "prediction_date": "2025-09-30",
      "price": 135.59,
      "rate_regime": "stable",
      "rsi": 66.7,
      "vix": 16.3,
      "env_score": 70,
      "tech_score": 50,
      "fund_score": 58,
      "composite": 60.4,
      "base_30d_pct": 2.0,
      "base_60d_pct": 3.5,
      "base_90d_pct": 5.0,
      "confidence": 67,
      "actual_30d_pct": 6.0,
      "hit_target_30d": "True",
      "actual_60d_pct": 15.0,
      "hit_target_60d": "True",
      "actual_90d_pct": 31.3,
      "hit_target_90d": "True"
    },
    {
      "prediction_date": "2025-12-29",
      "price": 168.74,
      "rate_regime": "stable",
      "rsi": 63.4,
      "vix": 14.2,
      "env_score": 65,
      "tech_score": 40,
      "fund_score": 58,
      "composite": 55.4,
      "base_30d_pct": 1.2,
      "base_60d_pct": 2.1,
      "base_90d_pct": 3.0,
      "confidence": 62,
      "actual_30d_pct": 5.2,
      "hit_target_30d": "True",
      "actual_60d_pct": -4.7,
      "hit_target_60d": "False",
      "actual_90d_pct": 12.1,
      "hit_target_90d": "True"
    }
  ],
  "mistake_vault": [
    {
      "prediction_date": "2020-01-30",
      "predicted_90d": 5.0,
      "actual_90d": 17.9,
      "error": 12.9,
      "direction_correct": "True",
      "composite_score": 63.1,
      "fund_score": 67,
      "rate_regime": "stable",
      "rsi": 51.2,
      "vix": 15.5,
      "root_cause": "Model underestimated upside"
    },
    {
      "prediction_date": "2020-04-29",
      "predicted_90d": 2.0,
      "actual_90d": 50.0,
      "error": 48.0,
      "direction_correct": "True",
      "composite_score": 56.1,
      "fund_score": 67,
      "rate_regime": "falling",
      "rsi": 64.7,
      "vix": 31.2,
      "root_cause": "Model underestimated upside"
    },
    {
      "prediction_date": "2020-07-28",
      "predicted_90d": 5.0,
      "actual_90d": 55.4,
      "error": 50.4,
      "direction_correct": "True",
      "composite_score": 59.5,
      "fund_score": 67,
      "rate_regime": "stable",
      "rsi": 76.6,
      "vix": 25.4,
      "root_cause": "Model underestimated upside"
    },
    {
      "prediction_date": "2020-10-26",
      "predicted_90d": 7.0,
      "actual_90d": 75.7,
      "error": 68.7,
      "direction_correct": "True",
      "composite_score": 66.1,
      "fund_score": 67,
      "rate_regime": "stable",
      "rsi": 62.2,
      "vix": 32.5,
      "root_cause": "Model underestimated upside"
    },
    {
      "prediction_date": "2021-01-24",
      "predicted_90d": 5.0,
      "actual_90d": 38.1,
      "error": 33.1,
      "direction_correct": "True",
      "composite_score": 58.6,
      "fund_score": 52,
      "rate_regime": "stable",
      "rsi": 52.0,
      "vix": 21.3,
      "root_cause": "Model underestimated upside"
    },
    {
      "prediction_date": "2021-04-25",
      "predicted_90d": 5.0,
      "actual_90d": 54.3,
      "error": 49.3,
      "direction_correct": "True",
      "composite_score": 62.6,
      "fund_score": 52,
      "rate_regime": "stable",
      "rsi": 41.8,
      "vix": 18.7,
      "root_cause": "Model underestimated upside"
    },
    {
      "prediction_date": "2022-01-19",
      "predicted_90d": 3.0,
      "actual_90d": -25.3,
      "error": 28.3,
      "direction_correct": "False",
      "composite_score": 55.5,
      "fund_score": 45,
      "rate_regime": "stable",
      "rsi": 63.7,
      "vix": 23.9,
      "root_cause": "Model underestimated downside"
    },
    {
      "prediction_date": "2022-04-19",
      "predicted_90d": 5.0,
      "actual_90d": -15.9,
      "error": 20.9,
      "direction_correct": "False",
      "composite_score": 64.9,
      "fund_score": 45,
      "rate_regime": "stable",
      "rsi": 31.8,
      "vix": 21.4,
      "root_cause": "Model underestimated downside"
    },
    {
      "prediction_date": "2022-07-18",
      "predicted_90d": -8.0,
      "actual_90d": 7.3,
      "error": 15.3,
      "direction_correct": "False",
      "composite_score": 40.5,
      "fund_score": 45,
      "rate_regime": "rising",
      "rsi": 40.3,
      "vix": 25.3,
      "root_cause": "Model underestimated upside"
    },
    {
      "prediction_date": "2023-01-15",
      "predicted_90d": -4.0,
      "actual_90d": 38.4,
      "error": 42.4,
      "direction_correct": "False",
      "composite_score": 46.3,
      "fund_score": 83,
      "rate_regime": "rising",
      "rsi": 70.2,
      "vix": 18.8,
      "root_cause": "Model underestimated upside"
    },
    {
      "prediction_date": "2023-04-16",
      "predicted_90d": -4.0,
      "actual_90d": 36.2,
      "error": 40.2,
      "direction_correct": "False",
      "composite_score": 43.3,
      "fund_score": 83,
      "rate_regime": "rising",
      "rsi": 71.6,
      "vix": 17.8,
      "root_cause": "Model underestimated upside"
    },
    {
      "prediction_date": "2023-07-13",
      "predicted_90d": 3.0,
      "actual_90d": -24.1,
      "error": 27.1,
      "direction_correct": "False",
      "composite_score": 51.8,
      "fund_score": 83,
      "rate_regime": "stable",
      "rsi": 71.2,
      "vix": 13.6,
      "root_cause": "Model underestimated downside"
    },
    {
      "prediction_date": "2024-07-07",
      "predicted_90d": -3.0,
      "actual_90d": 15.6,
      "error": 18.6,
      "direction_correct": "False",
      "composite_score": 39.2,
      "fund_score": 26,
      "rate_regime": "stable",
      "rsi": 74.3,
      "vix": 12.1,
      "root_cause": "Model underestimated upside"
    },
    {
      "prediction_date": "2024-10-06",
      "predicted_90d": 5.0,
      "actual_90d": -14.0,
      "error": 19.0,
      "direction_correct": "False",
      "composite_score": 61.2,
      "fund_score": 26,
      "rate_regime": "stable",
      "rsi": 36.1,
      "vix": 20.5,
      "root_cause": "Model underestimated downside"
    },
    {
      "prediction_date": "2025-01-05",
      "predicted_90d": 2.0,
      "actual_90d": -14.0,
      "error": 16.0,
      "direction_correct": "False",
      "composite_score": 52.8,
      "fund_score": 58,
      "rate_regime": "falling",
      "rsi": 39.0,
      "vix": 17.9,
      "root_cause": "Model underestimated downside"
    },
    {
      "prediction_date": "2025-09-30",
      "predicted_90d": 5.0,
      "actual_90d": 31.3,
      "error": 26.3,
      "direction_correct": "True",
      "composite_score": 60.4,
      "fund_score": 58,
      "rate_regime": "stable",
      "rsi": 66.7,
      "vix": 16.3,
      "root_cause": "Model underestimated upside"
    }
  ]
}